{"v":"5.12.1","fr":60,"ip":70,"op":130,"w":430,"h":430,"nm":"wired-flat-2547-logo-youtube","ddd":0,"assets":[{"id":"comp_0","nm":"in-reveal","fr":60,"layers":[{"ddd":0,"ind":1,"ty":4,"nm":"mask 2","td":1,"sr":1,"ks":{"o":{"a":0,"k":100,"ix":11},"r":{"a":0,"k":0,"ix":10},"p":{"a":0,"k":[215,215,0],"ix":2,"l":2},"a":{"a":0,"k":[0,0,0],"ix":1,"l":2},"s":{"a":0,"k":[100,100,100],"ix":6,"l":2}},"ao":0,"shapes":[{"ty":"gr","it":[{"ind":0,"ty":"sh","ix":1,"ks":{"a":1,"k":[{"i":{"x":0.054,"y":1},"o":{"x":0.167,"y":0.167},"t":0,"s":[{"i":[[1.25,9.5],[5.055,-35.7],[-2.308,-9.75],[-6.501,35.966]],"o":[[-4.704,-35.748],[-1.558,11],[8.418,35.565],[1.808,-10]],"v":[[34.75,-12],[-35.135,-12],[-34.635,10.75],[34.75,10.75]],"c":true}]},{"i":{"x":0.667,"y":1},"o":{"x":0.333,"y":0},"t":13,"s":[{"i":[[6.308,35.5],[6.308,-35.5],[-6.308,-35.999],[-6.308,36]],"o":[[-6.308,-35.5],[-6.308,35.5],[6.308,35.999],[6.308,-36]],"v":[[34.692,-134.5],[-34.692,-134.5],[-34.692,131.5],[34.692,131.5]],"c":true}]},{"i":{"x":0.667,"y":1},"o":{"x":0.333,"y":0},"t":28,"s":[{"i":[[32,14.1],[32,-14.1],[-32,-14.1],[-32,14.1]],"o":[[-32,-14.1],[-32,14.1],[32,14.1],[32,-14.1]],"v":[[176,-126.9],[-176,-126.9],[-176,126.9],[176,126.9]],"c":true}]},{"t":40,"s":[{"i":[[30,15],[30,-15],[-30,-15],[-30,15]],"o":[[-30,-15],[-30,15],[30,15],[30,-15]],"v":[[165,-135],[-165,-135],[-165,135],[165,135]],"c":true}]}],"ix":2},"nm":"Path 1","mn":"ADBE Vector Shape - Group","hd":false},{"ty":"fl","c":{"a":0,"k":[1,0,0,1],"ix":4},"o":{"a":0,"k":100,"ix":5},"r":1,"bm":0,"nm":"Fill 1","mn":"ADBE Vector Graphic - Fill","hd":false},{"ty":"tr","p":{"a":0,"k":[0,0],"ix":2},"a":{"a":0,"k":[0,0],"ix":1},"s":{"a":0,"k":[100,100],"ix":3},"r":{"a":0,"k":0,"ix":6},"o":{"a":0,"k":100,"ix":7},"sk":{"a":0,"k":0,"ix":4},"sa":{"a":0,"k":0,"ix":5},"nm":"Transform"}],"nm":"rectangle","np":2,"cix":2,"bm":0,"ix":1,"mn":"ADBE Vector Group","hd":false}],"ip":0,"op":98,"st":0,"ct":1,"bm":0},{"ddd":0,"ind":2,"ty":4,"nm":"triangle 6","parent":3,"tt":1,"tp":1,"sr":1,"ks":{"o":{"a":0,"k":100,"ix":11},"r":{"a":0,"k":-540,"ix":10},"p":{"a":0,"k":[1.196,0,0],"ix":2,"l":2},"a":{"a":0,"k":[0,0,0],"ix":1,"l":2},"s":{"a":0,"k":[100,100,100],"ix":6,"l":2}},"ao":0,"shapes":[{"ty":"gr","it":[{"ind":0,"ty":"sh","ix":1,"ks":{"a":0,"k":{"i":[[0,0],[0,0],[0,0],[0,2.399],[0,0],[-1.993,-1.335]],"o":[[0,0],[0,0],[-1.993,1.335],[0,0],[0,-2.399],[0,0]],"v":[[15,-56.913],[15,56.913],[-10.331,73.874],[-15,71.381],[-15,-71.381],[-10.331,-73.874]],"c":true},"ix":2},"nm":"Path 1","mn":"ADBE Vector Shape - Group","hd":false},{"ty":"fl","c":{"a":0,"k":[0.922,0.902,0.937,1],"ix":4,"x":"var $bm_rt;\n$bm_rt = comp('wired-flat-2547-logo-youtube').layer('control').effect('primary')('Color');"},"o":{"a":0,"k":50,"ix":5},"r":1,"bm":0,"nm":".primary","mn":"ADBE Vector Graphic - Fill","hd":false,"cl":"primary"},{"ty":"tr","p":{"a":0,"k":[-41.375,0],"ix":2},"a":{"a":0,"k":[0,0],"ix":1},"s":{"a":0,"k":[100,100],"ix":3},"r":{"a":0,"k":0,"ix":6},"o":{"a":0,"k":100,"ix":7},"sk":{"a":0,"k":0,"ix":4},"sa":{"a":0,"k":0,"ix":5},"nm":"Transform"}],"nm":"triangle-shadow","np":2,"cix":2,"bm":1,"ix":1,"mn":"ADBE Vector Group","hd":false},{"ty":"gr","it":[{"ind":0,"ty":"sh","ix":1,"ks":{"a":0,"k":{"i":[[0,0],[1.775,1.188],[0,0],[0,-2.399],[0,0],[-1.993,1.335]],"o":[[1.775,-1.188],[0,0],[-1.993,-1.335],[0,0],[0,2.399],[0,0]],"v":[[54.973,2.493],[54.973,-2.493],[-51.635,-73.874],[-56.304,-71.381],[-56.304,71.381],[-51.635,73.874]],"c":true},"ix":2},"nm":"Path 1","mn":"ADBE Vector Shape - Group","hd":false},{"ty":"rd","nm":"Round Corners 1","r":{"a":0,"k":3,"ix":1},"ix":2,"mn":"ADBE Vector Filter - RC","hd":false},{"ty":"fl","c":{"a":0,"k":[0.922,0.902,0.937,1],"ix":4,"x":"var $bm_rt;\n$bm_rt = comp('wired-flat-2547-logo-youtube').layer('control').effect('primary')('Color');"},"o":{"a":0,"k":100,"ix":5},"r":1,"bm":0,"nm":".primary","mn":"ADBE Vector Graphic - Fill","hd":false,"cl":"primary"},{"ty":"tr","p":{"a":0,"k":[0,0],"ix":2},"a":{"a":0,"k":[0,0],"ix":1},"s":{"a":0,"k":[100,100],"ix":3},"r":{"a":0,"k":0,"ix":6},"o":{"a":0,"k":100,"ix":7},"sk":{"a":0,"k":0,"ix":4},"sa":{"a":0,"k":0,"ix":5},"nm":"Transform"}],"nm":"triangle","np":3,"cix":2,"bm":0,"ix":2,"mn":"ADBE Vector Group","hd":false}],"ip":0,"op":300,"st":0,"ct":1,"bm":0},{"ddd":0,"ind":3,"ty":3,"nm":"triangle 5","sr":1,"ks":{"o":{"a":0,"k":100,"ix":11},"r":{"a":0,"k":0,"ix":10},"p":{"a":1,"k":[{"i":{"x":0.385,"y":1},"o":{"x":0.167,"y":0.167},"t":18,"s":[-30.5,215,0],"to":[0,0,0],"ti":[0,0,0]},{"i":{"x":0.397,"y":1},"o":{"x":0.46,"y":0},"t":34,"s":[269.5,215,0],"to":[0,0,0],"ti":[0,0,0]},{"t":60,"s":[229.5,215,0]}],"ix":2,"l":2},"a":{"a":0,"k":[0,0,0],"ix":1,"l":2},"s":{"a":0,"k":[-100,-100,100],"ix":6,"l":2}},"ao":0,"ip":34,"op":1800,"st":0,"ct":1,"bm":0},{"ddd":0,"ind":6,"ty":4,"nm":"rectangle 3","sr":1,"ks":{"o":{"a":0,"k":100,"ix":11},"r":{"a":0,"k":0,"ix":10},"p":{"a":0,"k":[215,215,0],"ix":2,"l":2},"a":{"a":0,"k":[0,0,0],"ix":1,"l":2},"s":{"a":0,"k":[100,100,100],"ix":6,"l":2}},"ao":0,"shapes":[{"ty":"gr","it":[{"ind":0,"ty":"sh","ix":1,"ks":{"a":1,"k":[{"i":{"x":0.043,"y":1},"o":{"x":0.167,"y":0.167},"t":1,"s":[{"i":[[-1.499,5.05],[-33.258,-1.112],[-0.143,-10.461],[-0.74,-42.55],[-16.198,-0.138],[-0.033,0.2]],"o":[[0.155,0.175],[-16.008,-1.112],[0.51,37.3],[0.156,8.998],[-34.198,0.112],[-1.499,-11.675]],"v":[[47.499,-11.925],[82.787,-38.513],[67.643,-15.05],[67.893,7.55],[84.977,37.263],[47.499,8.3]],"c":true}]},{"i":{"x":0.667,"y":1},"o":{"x":0.333,"y":0},"t":13,"s":[{"i":[[-7.345,35.8],[-29.883,-0.362],[-0.143,-10.461],[-0.74,-42.55],[-16.198,-0.138],[-0.033,0.2]],"o":[[0.155,0.175],[-16.008,-1.112],[0.51,37.3],[0.156,8.998],[-34.198,0.112],[-2.095,-34.55]],"v":[[48.816,-138.925],[82.883,-160.013],[67.835,-141.8],[67.74,129.05],[84.823,158.763],[47.345,129.8]],"c":true}]},{"i":{"x":0.667,"y":1},"o":{"x":0.333,"y":0},"t":28,"s":[{"i":[[-31.846,14],[-86.894,-0.772],[14.326,-6.298],[-31.846,-14],[-71.057,-0.631],[17.52,7.702]],"o":[[17.52,-7.702],[-71.056,0.631],[-31.846,14],[14.327,6.298],[-86.894,0.772],[-31.846,-14]],"v":[[-92.655,-126],[106.383,-136.394],[-44.885,-126],[-44.885,126],[106.385,136.394],[-92.655,126]],"c":true}]},{"t":40,"s":[{"i":[[-30,15],[-81.856,-0.827],[13.496,-6.748],[-30,-15],[-66.938,-0.677],[16.504,8.252]],"o":[[16.504,-8.252],[-66.937,0.677],[-30,15],[13.496,6.748],[-81.857,0.827],[-30,-15]],"v":[[-82.501,-135],[104.999,-146.137],[-37.501,-135],[-37.501,135],[105.001,146.137],[-82.501,135]],"c":true}]}],"ix":2},"nm":"Path 1","mn":"ADBE Vector Shape - Group","hd":false},{"ty":"fl","c":{"a":0,"k":[0.949,0.298,0,1],"ix":4,"x":"var $bm_rt;\n$bm_rt = comp('wired-flat-2547-logo-youtube').layer('control').effect('secondary')('Color');"},"o":{"a":0,"k":50,"ix":5},"r":1,"bm":0,"nm":".secondary","mn":"ADBE Vector Graphic - Fill","hd":false,"cl":"secondary"},{"ty":"tr","p":{"a":0,"k":[-82.5,0],"ix":2},"a":{"a":0,"k":[0,0],"ix":1},"s":{"a":0,"k":[100,100],"ix":3},"r":{"a":0,"k":0,"ix":6},"o":{"a":0,"k":100,"ix":7},"sk":{"a":0,"k":0,"ix":4},"sa":{"a":0,"k":0,"ix":5},"nm":"Transform"}],"nm":"rectangle-shadow","np":2,"cix":2,"bm":1,"ix":1,"mn":"ADBE Vector Group","hd":false},{"ty":"gr","it":[{"ind":0,"ty":"sh","ix":1,"ks":{"a":1,"k":[{"i":{"x":0.043,"y":1},"o":{"x":0.167,"y":0.167},"t":1,"s":[{"i":[[0.443,8.5],[19.242,0.563],[0.279,-0.2],[-1.625,-11.8],[-34.812,0.176],[-0.617,9.199]],"o":[[-0.929,-17.841],[-33.75,-0.988],[-1.75,5.55],[0.466,0.138],[26.337,-0.133],[0.443,-6.599]],"v":[[35.807,-9],[0.654,-38.887],[-35,-11.925],[-35,8.3],[2.529,37.262],[35.058,9.1]],"c":true}]},{"i":{"x":0.667,"y":1},"o":{"x":0.333,"y":0},"t":13,"s":[{"i":[[1.973,25.688],[26.375,-0.23],[0.279,-0.2],[-1.596,-35.05],[-34.812,0.176],[-1.04,9.161]],"o":[[-0.499,-6.5],[-30.125,0.262],[-7.096,36.05],[0.466,0.138],[26.337,-0.133],[6.596,-58.099]],"v":[[34.499,-135.625],[0.75,-160.387],[-33.683,-138.925],[-35.154,129.8],[2.375,158.762],[35.654,130.85]],"c":true}]},{"i":{"x":0.667,"y":1},"o":{"x":0.333,"y":0},"t":28,"s":[{"i":[[31.846,14],[79.276,0.03],[15.991,-7.03],[-31.846,-14],[-80.289,0.06],[-15.787,6.94]],"o":[[-15.855,-6.97],[-79.953,-0.03],[-31.846,14],[16.059,7.06],[78.932,-0.059],[31.846,-14]],"v":[[175.154,-126],[1.016,-136.5],[-175.154,-126],[-175.154,126],[2.035,136.499],[175.154,126]],"c":true}]},{"t":40,"s":[{"i":[[30,15],[74.68,0.032],[15.064,-7.532],[-30,-15],[-75.635,0.064],[-14.872,7.436]],"o":[[-14.936,-7.468],[-75.318,-0.032],[-30,15],[15.128,7.564],[74.357,-0.063],[30,-15]],"v":[[165,-135],[0.957,-146.25],[-165,-135],[-165,135],[1.917,146.249],[165,135]],"c":true}]}],"ix":2},"nm":"Path 1","mn":"ADBE Vector Shape - Group","hd":false},{"ty":"fl","c":{"a":0,"k":[0.949,0.298,0,1],"ix":4,"x":"var $bm_rt;\n$bm_rt = comp('wired-flat-2547-logo-youtube').layer('control').effect('secondary')('Color');"},"o":{"a":0,"k":100,"ix":5},"r":1,"bm":0,"nm":".secondary","mn":"ADBE Vector Graphic - Fill","hd":false,"cl":"secondary"},{"ty":"tr","p":{"a":0,"k":[0,0],"ix":2},"a":{"a":0,"k":[0,0],"ix":1},"s":{"a":0,"k":[100,100],"ix":3},"r":{"a":0,"k":0,"ix":6},"o":{"a":0,"k":100,"ix":7},"sk":{"a":0,"k":0,"ix":4},"sa":{"a":0,"k":0,"ix":5},"nm":"Transform"}],"nm":"rectangle","np":2,"cix":2,"bm":0,"ix":2,"mn":"ADBE Vector Group","hd":false}],"ip":1,"op":300,"st":0,"ct":1,"bm":0}]},{"id":"comp_1","nm":"hover-pinch","fr":60,"layers":[{"ddd":0,"ind":2,"ty":3,"nm":"triangle 2","parent":8,"sr":1,"ks":{"o":{"a":0,"k":100,"ix":11},"r":{"a":0,"k":0,"ix":10},"p":{"a":1,"k":[{"i":{"x":0.385,"y":1},"o":{"x":0.167,"y":0.167},"t":4,"s":[-245.5,0,0],"to":[0,0,0],"ti":[0,0,0]},{"i":{"x":0.397,"y":1},"o":{"x":0.46,"y":0},"t":26,"s":[54.5,0,0],"to":[0,0,0],"ti":[0,0,0]},{"t":60,"s":[14.5,0,0]}],"ix":2,"l":2},"a":{"a":0,"k":[0,0,0],"ix":1,"l":2},"s":{"a":0,"k":[-100,-100,100],"ix":6,"l":2}},"ao":0,"ip":0,"op":109,"st":0,"ct":1,"bm":0},{"ddd":0,"ind":3,"ty":4,"nm":"mask 2","td":1,"sr":1,"ks":{"o":{"a":0,"k":100,"ix":11},"r":{"a":0,"k":0,"ix":10},"p":{"a":0,"k":[215,215,0],"ix":2,"l":2},"a":{"a":0,"k":[0,0,0],"ix":1,"l":2},"s":{"a":1,"k":[{"i":{"x":[0.667,0.667,0.667],"y":[1,1,1]},"o":{"x":[0.333,0.333,0.333],"y":[0,0,0]},"t":0,"s":[100,100,100]},{"i":{"x":[0.07,0.07,0.07],"y":[1,1,1]},"o":{"x":[0.333,0.333,0.333],"y":[0,0,0]},"t":10,"s":[90,90,100]},{"t":60,"s":[100,100,100]}],"ix":6,"l":2}},"ao":0,"shapes":[{"ty":"gr","it":[{"ind":0,"ty":"sh","ix":1,"ks":{"a":0,"k":{"i":[[30,15],[30,-15],[-30,-15],[-30,15]],"o":[[-30,-15],[-30,15],[30,15],[30,-15]],"v":[[165,-135],[-165,-135],[-165,135],[165,135]],"c":true},"ix":2},"nm":"Path 1","mn":"ADBE Vector Shape - Group","hd":false},{"ty":"fl","c":{"a":0,"k":[1,0,0,1],"ix":4},"o":{"a":0,"k":100,"ix":5},"r":1,"bm":0,"nm":"Fill 1","mn":"ADBE Vector Graphic - Fill","hd":false},{"ty":"tr","p":{"a":0,"k":[0,0],"ix":2},"a":{"a":0,"k":[0,0],"ix":1},"s":{"a":0,"k":[100,100],"ix":3},"r":{"a":0,"k":0,"ix":6},"o":{"a":0,"k":100,"ix":7},"sk":{"a":0,"k":0,"ix":4},"sa":{"a":0,"k":0,"ix":5},"nm":"Transform"}],"nm":"rectangle","np":2,"cix":2,"bm":0,"ix":1,"mn":"ADBE Vector Group","hd":false}],"ip":0,"op":109,"st":0,"ct":1,"bm":0},{"ddd":0,"ind":4,"ty":4,"nm":"triangle 6","parent":2,"tt":1,"tp":3,"sr":1,"ks":{"o":{"a":0,"k":100,"ix":11},"r":{"a":0,"k":-540,"ix":10},"p":{"a":0,"k":[0.696,0,0],"ix":2,"l":2},"a":{"a":0,"k":[0,0,0],"ix":1,"l":2},"s":{"a":0,"k":[100,100,100],"ix":6,"l":2}},"ao":0,"shapes":[{"ty":"gr","it":[{"ind":0,"ty":"sh","ix":1,"ks":{"a":0,"k":{"i":[[0,0],[0,0],[0,0],[0,2.399],[0,0],[-1.993,-1.335]],"o":[[0,0],[0,0],[-1.993,1.335],[0,0],[0,-2.399],[0,0]],"v":[[15,-56.913],[15,56.913],[-10.331,73.874],[-15,71.381],[-15,-71.381],[-10.331,-73.874]],"c":true},"ix":2},"nm":"Path 1","mn":"ADBE Vector Shape - Group","hd":false},{"ty":"fl","c":{"a":0,"k":[0.922,0.902,0.937,1],"ix":4,"x":"var $bm_rt;\n$bm_rt = comp('wired-flat-2547-logo-youtube').layer('control').effect('primary')('Color');"},"o":{"a":0,"k":50,"ix":5},"r":1,"bm":0,"nm":".primary","mn":"ADBE Vector Graphic - Fill","hd":false,"cl":"primary"},{"ty":"tr","p":{"a":0,"k":[-41.375,0],"ix":2},"a":{"a":0,"k":[0,0],"ix":1},"s":{"a":0,"k":[100,100],"ix":3},"r":{"a":0,"k":0,"ix":6},"o":{"a":0,"k":100,"ix":7},"sk":{"a":0,"k":0,"ix":4},"sa":{"a":0,"k":0,"ix":5},"nm":"Transform"}],"nm":"triangle-shadow","np":2,"cix":2,"bm":1,"ix":1,"mn":"ADBE Vector Group","hd":false},{"ty":"gr","it":[{"ind":0,"ty":"sh","ix":1,"ks":{"a":0,"k":{"i":[[0,0],[1.775,1.188],[0,0],[0,-2.399],[0,0],[-1.993,1.335]],"o":[[1.775,-1.188],[0,0],[-1.993,-1.335],[0,0],[0,2.399],[0,0]],"v":[[54.973,2.493],[54.973,-2.493],[-51.635,-73.874],[-56.304,-71.381],[-56.304,71.381],[-51.635,73.874]],"c":true},"ix":2},"nm":"Path 1","mn":"ADBE Vector Shape - Group","hd":false},{"ty":"rd","nm":"Round Corners 1","r":{"a":0,"k":3,"ix":1},"ix":2,"mn":"ADBE Vector Filter - RC","hd":false},{"ty":"fl","c":{"a":0,"k":[0.922,0.902,0.937,1],"ix":4,"x":"var $bm_rt;\n$bm_rt = comp('wired-flat-2547-logo-youtube').layer('control').effect('primary')('Color');"},"o":{"a":0,"k":100,"ix":5},"r":1,"bm":0,"nm":".primary","mn":"ADBE Vector Graphic - Fill","hd":false,"cl":"primary"},{"ty":"tr","p":{"a":0,"k":[0,0],"ix":2},"a":{"a":0,"k":[0,0],"ix":1},"s":{"a":0,"k":[100,100],"ix":3},"r":{"a":0,"k":0,"ix":6},"o":{"a":0,"k":100,"ix":7},"sk":{"a":0,"k":0,"ix":4},"sa":{"a":0,"k":0,"ix":5},"nm":"Transform"}],"nm":"triangle","np":3,"cix":2,"bm":0,"ix":2,"mn":"ADBE Vector Group","hd":false}],"ip":0,"op":399,"st":0,"ct":1,"bm":0},{"ddd":0,"ind":5,"ty":3,"nm":"triangle","parent":8,"sr":1,"ks":{"o":{"a":0,"k":100,"ix":11},"r":{"a":0,"k":0,"ix":10},"p":{"a":1,"k":[{"i":{"x":0.833,"y":0.833},"o":{"x":0.333,"y":0},"t":0,"s":[14.5,0,0],"to":[0,0,0],"ti":[0,0,0]},{"t":14,"s":[254.5,0,0]}],"ix":2,"l":2},"a":{"a":0,"k":[0,0,0],"ix":1,"l":2},"s":{"a":0,"k":[-100,-100,100],"ix":6,"l":2}},"ao":0,"ip":0,"op":107,"st":0,"ct":1,"bm":0},{"ddd":0,"ind":6,"ty":4,"nm":"mask 3","td":1,"sr":1,"ks":{"o":{"a":0,"k":100,"ix":11},"r":{"a":0,"k":0,"ix":10},"p":{"a":0,"k":[215,215,0],"ix":2,"l":2},"a":{"a":0,"k":[0,0,0],"ix":1,"l":2},"s":{"a":1,"k":[{"i":{"x":[0.667,0.667,0.667],"y":[1,1,1]},"o":{"x":[0.333,0.333,0.333],"y":[0,0,0]},"t":0,"s":[100,100,100]},{"i":{"x":[0.07,0.07,0.07],"y":[1,1,1]},"o":{"x":[0.333,0.333,0.333],"y":[0,0,0]},"t":10,"s":[90,90,100]},{"t":60,"s":[100,100,100]}],"ix":6,"l":2}},"ao":0,"shapes":[{"ty":"gr","it":[{"ind":0,"ty":"sh","ix":1,"ks":{"a":0,"k":{"i":[[30,15],[30,-15],[-30,-15],[-30,15]],"o":[[-30,-15],[-30,15],[30,15],[30,-15]],"v":[[165,-135],[-165,-135],[-165,135],[165,135]],"c":true},"ix":2},"nm":"Path 1","mn":"ADBE Vector Shape - Group","hd":false},{"ty":"fl","c":{"a":0,"k":[1,0,0,1],"ix":4},"o":{"a":0,"k":100,"ix":5},"r":1,"bm":0,"nm":"Fill 1","mn":"ADBE Vector Graphic - Fill","hd":false},{"ty":"tr","p":{"a":0,"k":[0,0],"ix":2},"a":{"a":0,"k":[0,0],"ix":1},"s":{"a":0,"k":[100,100],"ix":3},"r":{"a":0,"k":0,"ix":6},"o":{"a":0,"k":100,"ix":7},"sk":{"a":0,"k":0,"ix":4},"sa":{"a":0,"k":0,"ix":5},"nm":"Transform"}],"nm":"rectangle","np":2,"cix":2,"bm":0,"ix":1,"mn":"ADBE Vector Group","hd":false}],"ip":0,"op":1899,"st":0,"ct":1,"bm":0},{"ddd":0,"ind":7,"ty":4,"nm":"triangle 5","parent":5,"tt":1,"tp":6,"sr":1,"ks":{"o":{"a":0,"k":100,"ix":11},"r":{"a":0,"k":-180,"ix":10},"p":{"a":0,"k":[1.196,0,0],"ix":2,"l":2},"a":{"a":0,"k":[0,0,0],"ix":1,"l":2},"s":{"a":0,"k":[100,100,100],"ix":6,"l":2}},"ao":0,"shapes":[{"ty":"gr","it":[{"ind":0,"ty":"sh","ix":1,"ks":{"a":0,"k":{"i":[[0,0],[0,0],[0,0],[0,2.399],[0,0],[-1.993,-1.335]],"o":[[0,0],[0,0],[-1.993,1.335],[0,0],[0,-2.399],[0,0]],"v":[[15,-56.913],[15,56.913],[-10.331,73.874],[-15,71.381],[-15,-71.381],[-10.331,-73.874]],"c":true},"ix":2},"nm":"Path 1","mn":"ADBE Vector Shape - Group","hd":false},{"ty":"fl","c":{"a":0,"k":[0.922,0.902,0.937,1],"ix":4,"x":"var $bm_rt;\n$bm_rt = comp('wired-flat-2547-logo-youtube').layer('control').effect('primary')('Color');"},"o":{"a":0,"k":50,"ix":5},"r":1,"bm":0,"nm":".primary","mn":"ADBE Vector Graphic - Fill","hd":false,"cl":"primary"},{"ty":"tr","p":{"a":0,"k":[-41.375,0],"ix":2},"a":{"a":0,"k":[0,0],"ix":1},"s":{"a":0,"k":[100,100],"ix":3},"r":{"a":0,"k":0,"ix":6},"o":{"a":0,"k":100,"ix":7},"sk":{"a":0,"k":0,"ix":4},"sa":{"a":0,"k":0,"ix":5},"nm":"Transform"}],"nm":"triangle-shadow","np":2,"cix":2,"bm":1,"ix":1,"mn":"ADBE Vector Group","hd":false},{"ty":"gr","it":[{"ind":0,"ty":"sh","ix":1,"ks":{"a":0,"k":{"i":[[0,0],[1.775,1.188],[0,0],[0,-2.399],[0,0],[-1.993,1.335]],"o":[[1.775,-1.188],[0,0],[-1.993,-1.335],[0,0],[0,2.399],[0,0]],"v":[[54.973,2.493],[54.973,-2.493],[-51.635,-73.874],[-56.304,-71.381],[-56.304,71.381],[-51.635,73.874]],"c":true},"ix":2},"nm":"Path 1","mn":"ADBE Vector Shape - Group","hd":false},{"ty":"rd","nm":"Round Corners 1","r":{"a":0,"k":3,"ix":1},"ix":2,"mn":"ADBE Vector Filter - RC","hd":false},{"ty":"fl","c":{"a":0,"k":[0.922,0.902,0.937,1],"ix":4,"x":"var $bm_rt;\n$bm_rt = comp('wired-flat-2547-logo-youtube').layer('control').effect('primary')('Color');"},"o":{"a":0,"k":100,"ix":5},"r":1,"bm":0,"nm":".primary","mn":"ADBE Vector Graphic - Fill","hd":false,"cl":"primary"},{"ty":"tr","p":{"a":0,"k":[0,0],"ix":2},"a":{"a":0,"k":[0,0],"ix":1},"s":{"a":0,"k":[100,100],"ix":3},"r":{"a":0,"k":0,"ix":6},"o":{"a":0,"k":100,"ix":7},"sk":{"a":0,"k":0,"ix":4},"sa":{"a":0,"k":0,"ix":5},"nm":"Transform"}],"nm":"triangle","np":3,"cix":2,"bm":0,"ix":2,"mn":"ADBE Vector Group","hd":false}],"ip":0,"op":399,"st":0,"ct":1,"bm":0},{"ddd":0,"ind":8,"ty":3,"nm":"rectangle","sr":1,"ks":{"o":{"a":0,"k":100,"ix":11},"r":{"a":0,"k":0,"ix":10},"p":{"a":0,"k":[215,215,0],"ix":2,"l":2},"a":{"a":0,"k":[0,0,0],"ix":1,"l":2},"s":{"a":1,"k":[{"i":{"x":[0.667,0.667,0.667],"y":[1,1,1]},"o":{"x":[0.333,0.333,0.333],"y":[0,0,0]},"t":0,"s":[100,100,100]},{"i":{"x":[0.07,0.07,0.07],"y":[1,1,1]},"o":{"x":[0.333,0.333,0.333],"y":[0,0,0]},"t":10,"s":[90,90,100]},{"t":60,"s":[100,100,100]}],"ix":6,"l":2}},"ao":0,"ip":0,"op":1899,"st":0,"ct":1,"bm":0},{"ddd":0,"ind":9,"ty":4,"nm":"rectangle 2","parent":8,"sr":1,"ks":{"o":{"a":0,"k":100,"ix":11},"r":{"a":0,"k":0,"ix":10},"p":{"a":0,"k":[0,0,0],"ix":2,"l":2},"a":{"a":0,"k":[0,0,0],"ix":1,"l":2},"s":{"a":0,"k":[100,100,100],"ix":6,"l":2}},"ao":0,"shapes":[{"ty":"gr","it":[{"ind":0,"ty":"sh","ix":1,"ks":{"a":0,"k":{"i":[[-30,15],[-81.856,-0.827],[13.496,-6.748],[-30,-15],[-66.938,-0.677],[16.504,8.252]],"o":[[16.504,-8.252],[-66.937,0.677],[-30,15],[13.496,6.748],[-81.857,0.827],[-30,-15]],"v":[[-82.501,-135],[104.999,-146.137],[-37.501,-135],[-37.501,135],[105.001,146.137],[-82.501,135]],"c":true},"ix":2},"nm":"Path 1","mn":"ADBE Vector Shape - Group","hd":false},{"ty":"fl","c":{"a":0,"k":[0.949,0.298,0,1],"ix":4,"x":"var $bm_rt;\n$bm_rt = comp('wired-flat-2547-logo-youtube').layer('control').effect('secondary')('Color');"},"o":{"a":0,"k":50,"ix":5},"r":1,"bm":0,"nm":".secondary","mn":"ADBE Vector Graphic - Fill","hd":false,"cl":"secondary"},{"ty":"tr","p":{"a":0,"k":[-82.5,0],"ix":2},"a":{"a":0,"k":[0,0],"ix":1},"s":{"a":0,"k":[100,100],"ix":3},"r":{"a":0,"k":0,"ix":6},"o":{"a":0,"k":100,"ix":7},"sk":{"a":0,"k":0,"ix":4},"sa":{"a":0,"k":0,"ix":5},"nm":"Transform"}],"nm":"rectangle-shadow","np":2,"cix":2,"bm":1,"ix":1,"mn":"ADBE Vector Group","hd":false},{"ty":"gr","it":[{"ind":0,"ty":"sh","ix":1,"ks":{"a":0,"k":{"i":[[30,15],[30,-15],[-30,-15],[-30,15]],"o":[[-30,-15],[-30,15],[30,15],[30,-15]],"v":[[165,-135],[-165,-135],[-165,135],[165,135]],"c":true},"ix":2},"nm":"Path 1","mn":"ADBE Vector Shape - Group","hd":false},{"ty":"fl","c":{"a":0,"k":[0.949,0.298,0,1],"ix":4,"x":"var $bm_rt;\n$bm_rt = comp('wired-flat-2547-logo-youtube').layer('control').effect('secondary')('Color');"},"o":{"a":0,"k":100,"ix":5},"r":1,"bm":0,"nm":".secondary","mn":"ADBE Vector Graphic - Fill","hd":false,"cl":"secondary"},{"ty":"tr","p":{"a":0,"k":[0,0],"ix":2},"a":{"a":0,"k":[0,0],"ix":1},"s":{"a":0,"k":[100,100],"ix":3},"r":{"a":0,"k":0,"ix":6},"o":{"a":0,"k":100,"ix":7},"sk":{"a":0,"k":0,"ix":4},"sa":{"a":0,"k":0,"ix":5},"nm":"Transform"}],"nm":"rectangle","np":2,"cix":2,"bm":0,"ix":2,"mn":"ADBE Vector Group","hd":false}],"ip":0,"op":399,"st":0,"ct":1,"bm":0}]},{"id":"comp_2","nm":"morph-logotype","fr":60,"layers":[{"ddd":0,"ind":1,"ty":4,"nm":"mask","td":1,"sr":1,"ks":{"o":{"a":0,"k":100,"ix":11},"r":{"a":0,"k":0,"ix":10},"p":{"a":0,"k":[215,215,0],"ix":2,"l":2},"a":{"a":0,"k":[0,0,0],"ix":1,"l":2},"s":{"a":0,"k":[100,100,100],"ix":6,"l":2}},"ao":0,"shapes":[{"ty":"gr","it":[{"ind":0,"ty":"sh","ix":1,"ks":{"a":1,"k":[{"i":{"x":0.833,"y":0.833},"o":{"x":0.6,"y":0},"t":0,"s":[{"i":[[5.715,2.857],[13.305,1.559],[66.875,-6.717],[5.141,-2.57],[3.441,-14.419],[-11.723,-53.276],[-5.715,-2.857],[-15.79,-1.656],[-60.689,7.587],[-4.128,2.064],[-3.562,16.569],[11.429,51.939]],"o":[[-4.42,-2.21],[-61.523,-7.208],[-16.821,1.689],[-5.347,2.673],[-12.188,51.075],[3.538,16.076],[4.936,2.468],[66.98,7.024],[11.967,-1.496],[5.822,-2.911],[11.298,-52.548],[-3.538,-16.075]],"v":[[165,-135],[137.644,-140.653],[-130.85,-141.39],[-165,-135],[-178.181,-108.087],[-178.878,105.044],[-165,135],[-132.842,141.185],[140.231,140.34],[165,135],[179.076,104.136],[178.878,-105.046]],"c":true}]},{"i":{"x":0.4,"y":1},"o":{"x":0.167,"y":0.167},"t":15,"s":[{"i":[[7.251,4.085],[17.102,0.779],[61.294,-3.359],[5.304,-3.155],[1.72,-14.743],[-5.862,-42.084],[-5.759,-3.531],[-19.601,-0.839],[-56.883,3.823],[-4.442,2.612],[-1.698,16.519],[5.56,40.962]],"o":[[-4.769,-2.652],[-57.176,-3.604],[-20.614,0.845],[-6.556,3.993],[-6.094,40.601],[1.769,16.116],[5.335,3.312],[61.773,3.538],[15.717,-0.759],[5.804,-3.377],[5.496,-41.37],[-1.686,-16.116]],"v":[[154.357,-73.906],[124.727,-80.452],[-117.879,-80.82],[-154.367,-74.156],[-169.216,-46.634],[-169.564,114.083],[-154.367,144.172],[-119.861,151.107],[127.422,150.681],[154.357,144.172],[169.69,113.326],[169.595,-44.068]],"c":true}]},{"t":30,"s":[{"i":[[8.786,5.313],[20.899,0],[55.712,0],[5.467,-3.74],[0,-15.068],[0,-30.893],[-5.803,-4.205],[-23.412,-0.022],[-53.077,0.058],[-4.756,3.16],[0.166,16.469],[-0.309,29.986]],"o":[[-5.118,-3.095],[-52.829,0],[-24.407,0],[-7.765,5.313],[0,30.127],[0,16.156],[5.735,4.156],[56.567,0.053],[19.467,-0.021],[5.786,-3.844],[-0.305,-30.192],[0.166,-16.156]],"v":[[143.714,-12.813],[111.81,-20.25],[-104.908,-20.25],[-143.735,-13.313],[-160.25,14.82],[-160.25,123.121],[-143.735,153.344],[-106.881,161.029],[114.612,161.021],[143.714,153.344],[160.305,122.516],[160.311,16.91]],"c":true}]}],"ix":2},"nm":"Path 1","mn":"ADBE Vector Shape - Group","hd":false},{"ty":"fl","c":{"a":0,"k":[1,0,0,1],"ix":4},"o":{"a":0,"k":100,"ix":5},"r":1,"bm":0,"nm":"Fill 1","mn":"ADBE Vector Graphic - Fill","hd":false},{"ty":"tr","p":{"a":0,"k":[0,0],"ix":2},"a":{"a":0,"k":[0,0],"ix":1},"s":{"a":0,"k":[100,100],"ix":3},"r":{"a":0,"k":0,"ix":6},"o":{"a":0,"k":100,"ix":7},"sk":{"a":0,"k":0,"ix":4},"sa":{"a":0,"k":0,"ix":5},"nm":"Transform"}],"nm":"rectangle","np":2,"cix":2,"bm":0,"ix":1,"mn":"ADBE Vector Group","hd":false}],"ip":0,"op":14,"st":0,"ct":1,"bm":0},{"ddd":0,"ind":2,"ty":4,"nm":"triangle 5","parent":3,"tt":1,"tp":1,"sr":1,"ks":{"o":{"a":0,"k":100,"ix":11},"r":{"a":0,"k":-540,"ix":10},"p":{"a":0,"k":[1.196,0,0],"ix":2,"l":2},"a":{"a":0,"k":[0,0,0],"ix":1,"l":2},"s":{"a":0,"k":[100,100,100],"ix":6,"l":2}},"ao":0,"shapes":[{"ty":"gr","it":[{"ind":0,"ty":"sh","ix":1,"ks":{"a":0,"k":{"i":[[0,0],[0,0],[0,0],[0,2.399],[0,0],[-1.993,-1.335]],"o":[[0,0],[0,0],[-1.993,1.335],[0,0],[0,-2.399],[0,0]],"v":[[15,-56.913],[15,56.913],[-10.331,73.874],[-15,71.381],[-15,-71.381],[-10.331,-73.874]],"c":true},"ix":2},"nm":"Path 1","mn":"ADBE Vector Shape - Group","hd":false},{"ty":"fl","c":{"a":0,"k":[0.922,0.902,0.937,1],"ix":4,"x":"var $bm_rt;\n$bm_rt = comp('wired-flat-2547-logo-youtube').layer('control').effect('primary')('Color');"},"o":{"a":0,"k":50,"ix":5},"r":1,"bm":0,"nm":".primary","mn":"ADBE Vector Graphic - Fill","hd":false,"cl":"primary"},{"ty":"tr","p":{"a":0,"k":[-41.375,0],"ix":2},"a":{"a":0,"k":[0,0],"ix":1},"s":{"a":0,"k":[100,100],"ix":3},"r":{"a":0,"k":0,"ix":6},"o":{"a":0,"k":100,"ix":7},"sk":{"a":0,"k":0,"ix":4},"sa":{"a":0,"k":0,"ix":5},"nm":"Transform"}],"nm":"triangle-shadow","np":2,"cix":2,"bm":1,"ix":1,"mn":"ADBE Vector Group","hd":false},{"ty":"gr","it":[{"ind":0,"ty":"sh","ix":1,"ks":{"a":0,"k":{"i":[[0,0],[1.775,1.188],[0,0],[0,-2.399],[0,0],[-1.993,1.335]],"o":[[1.775,-1.188],[0,0],[-1.993,-1.335],[0,0],[0,2.399],[0,0]],"v":[[54.973,2.493],[54.973,-2.493],[-51.635,-73.874],[-56.304,-71.381],[-56.304,71.381],[-51.635,73.874]],"c":true},"ix":2},"nm":"Path 1","mn":"ADBE Vector Shape - Group","hd":false},{"ty":"rd","nm":"Round Corners 1","r":{"a":0,"k":3,"ix":1},"ix":2,"mn":"ADBE Vector Filter - RC","hd":false},{"ty":"fl","c":{"a":0,"k":[0.922,0.902,0.937,1],"ix":4,"x":"var $bm_rt;\n$bm_rt = comp('wired-flat-2547-logo-youtube').layer('control').effect('primary')('Color');"},"o":{"a":0,"k":100,"ix":5},"r":1,"bm":0,"nm":".primary","mn":"ADBE Vector Graphic - Fill","hd":false,"cl":"primary"},{"ty":"tr","p":{"a":0,"k":[0,0],"ix":2},"a":{"a":0,"k":[0,0],"ix":1},"s":{"a":0,"k":[100,100],"ix":3},"r":{"a":0,"k":0,"ix":6},"o":{"a":0,"k":100,"ix":7},"sk":{"a":0,"k":0,"ix":4},"sa":{"a":0,"k":0,"ix":5},"nm":"Transform"}],"nm":"triangle","np":3,"cix":2,"bm":0,"ix":2,"mn":"ADBE Vector Group","hd":false}],"ip":0,"op":14,"st":0,"ct":1,"bm":0},{"ddd":0,"ind":3,"ty":3,"nm":"triangle 2","parent":14,"sr":1,"ks":{"o":{"a":0,"k":100,"ix":11},"r":{"a":0,"k":0,"ix":10},"p":{"a":1,"k":[{"i":{"x":0.833,"y":0.833},"o":{"x":0.333,"y":0},"t":0,"s":[14.5,0,0],"to":[0,0,0],"ti":[0,0,0]},{"t":14,"s":[254.5,0,0]}],"ix":2,"l":2},"a":{"a":0,"k":[0,0,0],"ix":1,"l":2},"s":{"a":0,"k":[-100,-100,100],"ix":6,"l":2}},"ao":0,"ip":5,"op":14,"st":0,"ct":1,"bm":0},{"ddd":0,"ind":5,"ty":4,"nm":"e","sr":1,"ks":{"o":{"a":0,"k":100,"ix":11},"r":{"a":0,"k":0,"ix":10},"p":{"a":0,"k":[215,282.5,0],"ix":2,"l":2},"a":{"a":0,"k":[0,0,0],"ix":1,"l":2},"s":{"a":0,"k":[100,100,100],"ix":6,"l":2}},"ao":0,"shapes":[{"ty":"gr","it":[{"ind":0,"ty":"sh","ix":1,"ks":{"a":1,"k":[{"i":{"x":0.4,"y":1},"o":{"x":0.6,"y":0},"t":0,"s":[{"i":[[0,0],[0,0],[-6.828,0],[0,0],[0,-6.828],[0,0]],"o":[[0,0],[0,-6.828],[0,0],[6.828,0],[0,0],[0,0]],"v":[[92.727,-52.545],[92.727,-89.636],[105.091,-102],[123.636,-102],[136,-89.636],[136,-52.545]],"c":true}]},{"t":30,"s":[{"i":[[0,0],[0,0],[-5.523,0],[0,0],[0,-5.523],[0,0]],"o":[[0,0],[0,-5.523],[0,0],[5.523,0],[0,0],[0,0]],"v":[[75,12.5],[75,-17.5],[85,-27.5],[100,-27.5],[110,-17.5],[110,12.5]],"c":true}]}],"ix":2},"nm":"e","mn":"ADBE Vector Shape - Group","hd":false},{"ty":"st","c":{"a":0,"k":[0.922,0.902,0.937,1],"ix":3,"x":"var $bm_rt;\n$bm_rt = comp('wired-flat-2547-logo-youtube').layer('control').effect('primary')('Color');"},"o":{"a":0,"k":100,"ix":4},"w":{"a":0,"k":7,"ix":5},"lc":2,"lj":2,"bm":0,"nm":".primary","mn":"ADBE Vector Graphic - Stroke","hd":false,"cl":"primary"},{"ty":"tm","s":{"a":1,"k":[{"i":{"x":[0.32],"y":[1]},"o":{"x":[0.167],"y":[0.167]},"t":17.875,"s":[0]},{"t":30,"s":[100]}],"ix":1},"e":{"a":0,"k":0,"ix":2},"o":{"a":0,"k":0,"ix":3},"m":1,"ix":3,"nm":"Trim Paths 1","mn":"ADBE Vector Filter - Trim","hd":false},{"ty":"tr","p":{"a":0,"k":[0,0],"ix":2},"a":{"a":0,"k":[0,0],"ix":1},"s":{"a":0,"k":[100,100],"ix":3},"r":{"a":0,"k":0,"ix":6},"o":{"a":0,"k":100,"ix":7},"sk":{"a":0,"k":0,"ix":4},"sa":{"a":0,"k":0,"ix":5},"nm":"Transform"}],"nm":"Vector 2","np":3,"cix":2,"bm":0,"ix":1,"mn":"ADBE Vector Group","hd":false},{"ty":"gr","it":[{"ind":0,"ty":"sh","ix":1,"ks":{"a":1,"k":[{"i":{"x":0.4,"y":1},"o":{"x":0.6,"y":0},"t":0,"s":[{"i":[[0,0],[0,0],[6.828,0],[0,0],[0,6.828],[0,0]],"o":[[0,0],[0,6.828],[0,0],[-6.828,0],[0,0],[0,0]],"v":[[136,-21.636],[136,-15.455],[123.636,-3.091],[105.091,-3.091],[92.727,-15.455],[92.727,-52.545]],"c":false}]},{"t":30,"s":[{"i":[[0,0],[0,0],[5.523,0],[0,0],[0,5.523],[0,0]],"o":[[0,0],[0,5.523],[0,0],[-5.523,0],[0,0],[0,0]],"v":[[110,37.5],[110,42.5],[100,52.5],[85,52.5],[75,42.5],[75,12.5]],"c":false}]}],"ix":2},"nm":"e","mn":"ADBE Vector Shape - Group","hd":false},{"ty":"st","c":{"a":0,"k":[0.922,0.902,0.937,1],"ix":3,"x":"var $bm_rt;\n$bm_rt = comp('wired-flat-2547-logo-youtube').layer('control').effect('primary')('Color');"},"o":{"a":0,"k":100,"ix":4},"w":{"a":0,"k":7,"ix":5},"lc":2,"lj":2,"bm":0,"nm":".primary","mn":"ADBE Vector Graphic - Stroke","hd":false,"cl":"primary"},{"ty":"tm","s":{"a":1,"k":[{"i":{"x":[0.833],"y":[0.833]},"o":{"x":[0.167],"y":[0.167]},"t":10.158,"s":[0]},{"t":17.875,"s":[100]}],"ix":1},"e":{"a":0,"k":0,"ix":2},"o":{"a":0,"k":0,"ix":3},"m":1,"ix":3,"nm":"Trim Paths 1","mn":"ADBE Vector Filter - Trim","hd":false},{"ty":"tr","p":{"a":0,"k":[0,0],"ix":2},"a":{"a":0,"k":[0,0],"ix":1},"s":{"a":0,"k":[100,100],"ix":3},"r":{"a":0,"k":0,"ix":6},"o":{"a":0,"k":100,"ix":7},"sk":{"a":0,"k":0,"ix":4},"sa":{"a":0,"k":0,"ix":5},"nm":"Transform"}],"nm":"Vector","np":3,"cix":2,"bm":0,"ix":2,"mn":"ADBE Vector Group","hd":false}],"ip":0,"op":1800,"st":0,"ct":1,"bm":0},{"ddd":0,"ind":6,"ty":4,"nm":"b","sr":1,"ks":{"o":{"a":0,"k":100,"ix":11},"r":{"a":0,"k":0,"ix":10},"p":{"a":0,"k":[215,282.5,0],"ix":2,"l":2},"a":{"a":0,"k":[0,0,0],"ix":1,"l":2},"s":{"a":0,"k":[100,100,100],"ix":6,"l":2}},"ao":0,"shapes":[{"ty":"gr","it":[{"ind":0,"ty":"sh","ix":1,"ks":{"a":1,"k":[{"i":{"x":0.4,"y":1},"o":{"x":0.6,"y":0},"t":0,"s":[{"i":[[0,0],[0,0]],"o":[[0,0],[0,0]],"v":[[12.364,-132.909],[12.364,-100.764]],"c":false}]},{"t":30,"s":[{"i":[[0,0],[0,0]],"o":[[0,0],[0,0]],"v":[[10,-52.5],[10,-26.5]],"c":false}]}],"ix":2},"nm":"b","mn":"ADBE Vector Shape - Group","hd":false},{"ty":"st","c":{"a":0,"k":[0.922,0.902,0.937,1],"ix":3,"x":"var $bm_rt;\n$bm_rt = comp('wired-flat-2547-logo-youtube').layer('control').effect('primary')('Color');"},"o":{"a":0,"k":100,"ix":4},"w":{"a":0,"k":7,"ix":5},"lc":2,"lj":1,"ml":4,"bm":0,"nm":".primary","mn":"ADBE Vector Graphic - Stroke","hd":false,"cl":"primary"},{"ty":"tm","s":{"a":1,"k":[{"i":{"x":[0.833],"y":[0.833]},"o":{"x":[0.167],"y":[0.167]},"t":7.105,"s":[0]},{"t":12,"s":[100]}],"ix":1},"e":{"a":0,"k":0,"ix":2},"o":{"a":0,"k":0,"ix":3},"m":1,"ix":3,"nm":"Trim Paths 1","mn":"ADBE Vector Filter - Trim","hd":false},{"ty":"tr","p":{"a":0,"k":[0,0],"ix":2},"a":{"a":0,"k":[0,0],"ix":1},"s":{"a":0,"k":[100,100],"ix":3},"r":{"a":0,"k":0,"ix":6},"o":{"a":0,"k":100,"ix":7},"sk":{"a":0,"k":0,"ix":4},"sa":{"a":0,"k":0,"ix":5},"nm":"Transform"}],"nm":"Vector 2","np":3,"cix":2,"bm":0,"ix":1,"mn":"ADBE Vector Group","hd":false},{"ty":"gr","it":[{"ind":0,"ty":"sh","ix":1,"ks":{"a":1,"k":[{"i":{"x":0.4,"y":1},"o":{"x":0.6,"y":0},"t":0,"s":[{"i":[[-6.828,0],[0,0],[0,6.828],[0,0],[6.828,0],[0,0],[0,0]],"o":[[0,0],[6.828,0],[0,0],[0,-6.828],[0,0],[0,0],[0,6.828]],"v":[[24.727,-3.091],[45.127,-3.091],[57.491,-15.455],[57.491,-88.4],[45.127,-100.764],[12.364,-100.764],[12.364,-15.455]],"c":true}]},{"t":30,"s":[{"i":[[-5.523,0],[0,0],[0,5.523],[0,0],[5.523,0],[0,0],[0,0]],"o":[[0,0],[5.523,0],[0,0],[0,-5.523],[0,0],[0,0],[0,5.523]],"v":[[20,52.5],[36.5,52.5],[46.5,42.5],[46.5,-16.5],[36.5,-26.5],[10,-26.5],[10,42.5]],"c":true}]}],"ix":2},"nm":"b","mn":"ADBE Vector Shape - Group","hd":false},{"ty":"st","c":{"a":0,"k":[0.922,0.902,0.937,1],"ix":3,"x":"var $bm_rt;\n$bm_rt = comp('wired-flat-2547-logo-youtube').layer('control').effect('primary')('Color');"},"o":{"a":0,"k":100,"ix":4},"w":{"a":0,"k":7,"ix":5},"lc":2,"lj":1,"ml":4,"bm":0,"nm":".primary","mn":"ADBE Vector Graphic - Stroke","hd":false,"cl":"primary"},{"ty":"tm","s":{"a":1,"k":[{"i":{"x":[0.32],"y":[1]},"o":{"x":[0.167],"y":[0.167]},"t":12,"s":[0]},{"t":30,"s":[100]}],"ix":1},"e":{"a":0,"k":0,"ix":2},"o":{"a":0,"k":-137,"ix":3},"m":1,"ix":3,"nm":"Trim Paths 1","mn":"ADBE Vector Filter - Trim","hd":false},{"ty":"tr","p":{"a":0,"k":[0,0],"ix":2},"a":{"a":0,"k":[0,0],"ix":1},"s":{"a":0,"k":[100,100],"ix":3},"r":{"a":0,"k":0,"ix":6},"o":{"a":0,"k":100,"ix":7},"sk":{"a":0,"k":0,"ix":4},"sa":{"a":0,"k":0,"ix":5},"nm":"Transform"}],"nm":"Vector","np":3,"cix":2,"bm":0,"ix":2,"mn":"ADBE Vector Group","hd":false}],"ip":0,"op":1800,"st":0,"ct":1,"bm":0},{"ddd":0,"ind":7,"ty":4,"nm":"u","sr":1,"ks":{"o":{"a":0,"k":100,"ix":11},"r":{"a":0,"k":0,"ix":10},"p":{"a":0,"k":[215,282.5,0],"ix":2,"l":2},"a":{"a":0,"k":[0,0,0],"ix":1,"l":2},"s":{"a":0,"k":[100,100,100],"ix":6,"l":2}},"ao":0,"shapes":[{"ty":"gr","it":[{"ind":0,"ty":"sh","ix":1,"ks":{"a":1,"k":[{"i":{"x":0.4,"y":1},"o":{"x":0.6,"y":0},"t":0,"s":[{"i":[[0,0],[0,0],[-6.828,0],[0,0],[0,6.828],[0,0]],"o":[[0,0],[0,6.828],[0,0],[6.828,0],[0,0],[0,0]],"v":[[-68,-102],[-68,-15.455],[-55.636,-3.091],[-37.091,-3.091],[-24.727,-15.455],[-24.727,-102]],"c":false}]},{"t":30,"s":[{"i":[[0,0],[0,0],[-5.523,0],[0,0],[0,5.523],[0,0]],"o":[[0,0],[0,5.523],[0,0],[5.523,0],[0,0],[0,0]],"v":[[-55,-27.5],[-55,42.5],[-45,52.5],[-30,52.5],[-20,42.5],[-20,-27.5]],"c":false}]}],"ix":2},"nm":"u","mn":"ADBE Vector Shape - Group","hd":false},{"ty":"st","c":{"a":0,"k":[0.922,0.902,0.937,1],"ix":3,"x":"var $bm_rt;\n$bm_rt = comp('wired-flat-2547-logo-youtube').layer('control').effect('primary')('Color');"},"o":{"a":0,"k":100,"ix":4},"w":{"a":0,"k":7,"ix":5},"lc":2,"lj":1,"ml":4,"bm":0,"nm":".primary","mn":"ADBE Vector Graphic - Stroke","hd":false,"cl":"primary"},{"ty":"tm","s":{"a":1,"k":[{"i":{"x":[0.32],"y":[1]},"o":{"x":[0.167],"y":[0.167]},"t":4.053,"s":[50]},{"t":20.841796875,"s":[0]}],"ix":1},"e":{"a":1,"k":[{"i":{"x":[0.32],"y":[1]},"o":{"x":[0.167],"y":[0.167]},"t":4.053,"s":[50]},{"t":20.841796875,"s":[100]}],"ix":2},"o":{"a":0,"k":0,"ix":3},"m":1,"ix":3,"nm":"Trim Paths 1","mn":"ADBE Vector Filter - Trim","hd":false},{"ty":"tr","p":{"a":0,"k":[0,0],"ix":2},"a":{"a":0,"k":[0,0],"ix":1},"s":{"a":0,"k":[100,100],"ix":3},"r":{"a":0,"k":0,"ix":6},"o":{"a":0,"k":100,"ix":7},"sk":{"a":0,"k":0,"ix":4},"sa":{"a":0,"k":0,"ix":5},"nm":"Transform"}],"nm":"Vector","np":3,"cix":2,"bm":0,"ix":1,"mn":"ADBE Vector Group","hd":false}],"ip":0,"op":1800,"st":0,"ct":1,"bm":0},{"ddd":0,"ind":8,"ty":4,"nm":"t","sr":1,"ks":{"o":{"a":0,"k":100,"ix":11},"r":{"a":0,"k":0,"ix":10},"p":{"a":0,"k":[215,282.5,0],"ix":2,"l":2},"a":{"a":0,"k":[0,0,0],"ix":1,"l":2},"s":{"a":0,"k":[100,100,100],"ix":6,"l":2}},"ao":0,"shapes":[{"ty":"gr","it":[{"ind":0,"ty":"sh","ix":1,"ks":{"a":1,"k":[{"i":{"x":0.4,"y":1},"o":{"x":0.6,"y":0},"t":0,"s":[{"i":[[0,0],[0,0]],"o":[[0,0],[0,0]],"v":[[-111.273,-132.909],[-136,-132.909]],"c":false}]},{"t":30,"s":[{"i":[[0,0],[0,0]],"o":[[0,0],[0,0]],"v":[[-90,-52.5],[-110,-52.5]],"c":false}]}],"ix":2},"nm":"t","mn":"ADBE Vector Shape - Group","hd":false},{"ind":1,"ty":"sh","ix":2,"ks":{"a":1,"k":[{"i":{"x":0.4,"y":1},"o":{"x":0.6,"y":0},"t":0,"s":[{"i":[[0,0],[0,0]],"o":[[0,0],[0,0]],"v":[[-111.273,-132.909],[-86.545,-132.909]],"c":false}]},{"t":30,"s":[{"i":[[0,0],[0,0]],"o":[[0,0],[0,0]],"v":[[-90,-52.5],[-70,-52.5]],"c":false}]}],"ix":2},"nm":"t","mn":"ADBE Vector Shape - Group","hd":false},{"ty":"st","c":{"a":0,"k":[0.922,0.902,0.937,1],"ix":3,"x":"var $bm_rt;\n$bm_rt = comp('wired-flat-2547-logo-youtube').layer('control').effect('primary')('Color');"},"o":{"a":0,"k":100,"ix":4},"w":{"a":0,"k":7,"ix":5},"lc":2,"lj":1,"ml":4,"bm":0,"nm":".primary","mn":"ADBE Vector Graphic - Stroke","hd":false,"cl":"primary"},{"ty":"tm","s":{"a":1,"k":[{"i":{"x":[0.32],"y":[1]},"o":{"x":[0.167],"y":[0.167]},"t":1,"s":[0]},{"t":17.7890625,"s":[100]}],"ix":1},"e":{"a":0,"k":0,"ix":2},"o":{"a":0,"k":0,"ix":3},"m":1,"ix":4,"nm":"Trim Paths 1","mn":"ADBE Vector Filter - Trim","hd":false},{"ty":"tr","p":{"a":0,"k":[0,0],"ix":2},"a":{"a":0,"k":[0,0],"ix":1},"s":{"a":0,"k":[100,100],"ix":3},"r":{"a":0,"k":0,"ix":6},"o":{"a":0,"k":100,"ix":7},"sk":{"a":0,"k":0,"ix":4},"sa":{"a":0,"k":0,"ix":5},"nm":"Transform"}],"nm":"Vector 2","np":4,"cix":2,"bm":0,"ix":1,"mn":"ADBE Vector Group","hd":false},{"ty":"gr","it":[{"ind":0,"ty":"sh","ix":1,"ks":{"a":1,"k":[{"i":{"x":0.4,"y":1},"o":{"x":0.6,"y":0},"t":0,"s":[{"i":[[0,0],[0,0]],"o":[[0,0],[0,0]],"v":[[-111.273,-132.909],[-111.273,-3.091]],"c":false}]},{"t":30,"s":[{"i":[[0,0],[0,0]],"o":[[0,0],[0,0]],"v":[[-90,-52.5],[-90,52.5]],"c":false}]}],"ix":2},"nm":"t","mn":"ADBE Vector Shape - Group","hd":false},{"ty":"st","c":{"a":0,"k":[0.922,0.902,0.937,1],"ix":3,"x":"var $bm_rt;\n$bm_rt = comp('wired-flat-2547-logo-youtube').layer('control').effect('primary')('Color');"},"o":{"a":0,"k":100,"ix":4},"w":{"a":0,"k":7,"ix":5},"lc":2,"lj":1,"ml":4,"bm":0,"nm":".primary","mn":"ADBE Vector Graphic - Stroke","hd":false,"cl":"primary"},{"ty":"tm","s":{"a":1,"k":[{"i":{"x":[0.32],"y":[1]},"o":{"x":[0.167],"y":[0.167]},"t":1,"s":[0]},{"t":17.7890625,"s":[100]}],"ix":1},"e":{"a":0,"k":0,"ix":2},"o":{"a":0,"k":0,"ix":3},"m":1,"ix":3,"nm":"Trim Paths 1","mn":"ADBE Vector Filter - Trim","hd":false},{"ty":"tr","p":{"a":0,"k":[0,0],"ix":2},"a":{"a":0,"k":[0,0],"ix":1},"s":{"a":0,"k":[100,100],"ix":3},"r":{"a":0,"k":0,"ix":6},"o":{"a":0,"k":100,"ix":7},"sk":{"a":0,"k":0,"ix":4},"sa":{"a":0,"k":0,"ix":5},"nm":"Transform"}],"nm":"Vector","np":3,"cix":2,"bm":0,"ix":2,"mn":"ADBE Vector Group","hd":false}],"ip":0,"op":1800,"st":0,"ct":1,"bm":0},{"ddd":0,"ind":9,"ty":4,"nm":"u","sr":1,"ks":{"o":{"a":0,"k":100,"ix":11},"r":{"a":0,"k":0,"ix":10},"p":{"a":0,"k":[277.5,155,0],"ix":2,"l":2},"a":{"a":0,"k":[65,57.5,0],"ix":1,"l":2},"s":{"a":0,"k":[100,100,100],"ix":6,"l":2}},"ao":0,"shapes":[{"ty":"gr","it":[{"ind":0,"ty":"sh","ix":1,"ks":{"a":0,"k":{"i":[[0,0],[0,0],[-5.523,0],[0,0],[0,5.523],[0,0]],"o":[[0,0],[0,5.523],[0,0],[5.523,0],[0,0],[0,0]],"v":[[47.5,-22.5],[47.5,47.5],[57.5,57.5],[72.5,57.5],[82.5,47.5],[82.5,-22.5]],"c":false},"ix":2},"nm":"Path 5","mn":"ADBE Vector Shape - Group","hd":false},{"ty":"st","c":{"a":0,"k":[0.227,0.2,0.278,1],"ix":3,"x":"var $bm_rt;\n$bm_rt = comp('wired-flat-2547-logo-youtube').layer('control').effect('tertiary')('Color');"},"o":{"a":0,"k":100,"ix":4},"w":{"a":0,"k":7,"ix":5},"lc":2,"lj":2,"bm":0,"nm":".tertiary","mn":"ADBE Vector Graphic - Stroke","hd":false,"cl":"tertiary"},{"ty":"tm","s":{"a":1,"k":[{"i":{"x":[0.32],"y":[1]},"o":{"x":[0.167],"y":[0.167]},"t":19,"s":[50]},{"t":30,"s":[0]}],"ix":1},"e":{"a":1,"k":[{"i":{"x":[0.32],"y":[1]},"o":{"x":[0.167],"y":[0.167]},"t":19,"s":[50]},{"t":30,"s":[100]}],"ix":2},"o":{"a":0,"k":0,"ix":3},"m":1,"ix":3,"nm":"Trim Paths 1","mn":"ADBE Vector Filter - Trim","hd":false},{"ty":"tr","p":{"a":0,"k":[0,0],"ix":2},"a":{"a":0,"k":[0,0],"ix":1},"s":{"a":0,"k":[100,100],"ix":3},"r":{"a":0,"k":0,"ix":6},"o":{"a":0,"k":100,"ix":7},"sk":{"a":0,"k":0,"ix":4},"sa":{"a":0,"k":0,"ix":5},"nm":"Transform"}],"nm":"Vector","np":3,"cix":2,"bm":0,"ix":1,"mn":"ADBE Vector Group","hd":false}],"ip":19,"op":1812,"st":12,"ct":1,"bm":0},{"ddd":0,"ind":10,"ty":4,"nm":"o","sr":1,"ks":{"o":{"a":0,"k":100,"ix":11},"r":{"a":0,"k":0,"ix":10},"p":{"a":0,"k":[212.5,155,0],"ix":2,"l":2},"a":{"a":0,"k":[0,57.5,0],"ix":1,"l":2},"s":{"a":0,"k":[100,100,100],"ix":6,"l":2}},"ao":0,"shapes":[{"ty":"gr","it":[{"ind":0,"ty":"sh","ix":1,"ks":{"a":0,"k":{"i":[[0,0],[0,-5.523],[0,0],[-5.523,0],[0,0],[0,5.523],[0,0],[5.523,0]],"o":[[-5.523,0],[0,0],[0,5.523],[0,0],[5.523,0],[0,0],[0,-5.523],[0,0]],"v":[[-7.5,-22.5],[-17.5,-12.5],[-17.5,47.5],[-7.5,57.5],[7.5,57.5],[17.5,47.5],[17.5,-12.5],[7.5,-22.5]],"c":true},"ix":2},"nm":"Path 1","mn":"ADBE Vector Shape - Group","hd":false},{"ty":"tm","s":{"a":1,"k":[{"i":{"x":[0.32],"y":[1]},"o":{"x":[0.167],"y":[0.167]},"t":18,"s":[50]},{"t":29,"s":[0]}],"ix":1},"e":{"a":1,"k":[{"i":{"x":[0.32],"y":[1]},"o":{"x":[0.167],"y":[0.167]},"t":18,"s":[50]},{"t":29,"s":[100]}],"ix":2},"o":{"a":0,"k":-12,"ix":3},"m":1,"ix":2,"nm":"Trim Paths 1","mn":"ADBE Vector Filter - Trim","hd":false},{"ty":"st","c":{"a":0,"k":[0.227,0.2,0.278,1],"ix":3,"x":"var $bm_rt;\n$bm_rt = comp('wired-flat-2547-logo-youtube').layer('control').effect('tertiary')('Color');"},"o":{"a":0,"k":100,"ix":4},"w":{"a":0,"k":7,"ix":5},"lc":2,"lj":2,"bm":0,"nm":".tertiary","mn":"ADBE Vector Graphic - Stroke","hd":false,"cl":"tertiary"},{"ty":"tr","p":{"a":0,"k":[0,0],"ix":2},"a":{"a":0,"k":[0,0],"ix":1},"s":{"a":0,"k":[100,100],"ix":3},"r":{"a":0,"k":0,"ix":6},"o":{"a":0,"k":100,"ix":7},"sk":{"a":0,"k":0,"ix":4},"sa":{"a":0,"k":0,"ix":5},"nm":"Transform"}],"nm":"Vector","np":3,"cix":2,"bm":0,"ix":1,"mn":"ADBE Vector Group","hd":false}],"ip":18,"op":1811,"st":11,"ct":1,"bm":0},{"ddd":0,"ind":11,"ty":4,"nm":"Y","sr":1,"ks":{"o":{"a":0,"k":100,"ix":11},"r":{"a":0,"k":0,"ix":10},"p":{"a":0,"k":[155,155,0],"ix":2,"l":2},"a":{"a":0,"k":[-57.5,57.5,0],"ix":1,"l":2},"s":{"a":0,"k":[100,100,100],"ix":6,"l":2}},"ao":0,"shapes":[{"ty":"gr","it":[{"ind":0,"ty":"sh","ix":1,"ks":{"a":0,"k":{"i":[[0,0],[0,0]],"o":[[0,0],[0,0]],"v":[[-57.5,12.5],[-82.5,-57.5]],"c":false},"ix":2},"nm":"Path 2","mn":"ADBE Vector Shape - Group","hd":false},{"ind":1,"ty":"sh","ix":2,"ks":{"a":0,"k":{"i":[[0,0],[0,0]],"o":[[0,0],[0,0]],"v":[[-57.5,12.5],[-32.5,-57.5]],"c":false},"ix":2},"nm":"Path 3","mn":"ADBE Vector Shape - Group","hd":false},{"ty":"tm","s":{"a":0,"k":0,"ix":1},"e":{"a":1,"k":[{"i":{"x":[0.32],"y":[1]},"o":{"x":[0.167],"y":[0.167]},"t":20.25,"s":[0]},{"t":28,"s":[100]}],"ix":2},"o":{"a":0,"k":0,"ix":3},"m":1,"ix":3,"nm":"Trim Paths 1","mn":"ADBE Vector Filter - Trim","hd":false},{"ty":"st","c":{"a":0,"k":[0.227,0.2,0.278,1],"ix":3,"x":"var $bm_rt;\n$bm_rt = comp('wired-flat-2547-logo-youtube').layer('control').effect('tertiary')('Color');"},"o":{"a":0,"k":100,"ix":4},"w":{"a":0,"k":7,"ix":5},"lc":2,"lj":2,"bm":0,"nm":".tertiary","mn":"ADBE Vector Graphic - Stroke","hd":false,"cl":"tertiary"},{"ty":"tr","p":{"a":0,"k":[0,0],"ix":2},"a":{"a":0,"k":[0,0],"ix":1},"s":{"a":0,"k":[100,100],"ix":3},"r":{"a":0,"k":0,"ix":6},"o":{"a":0,"k":100,"ix":7},"sk":{"a":0,"k":0,"ix":4},"sa":{"a":0,"k":0,"ix":5},"nm":"Transform"}],"nm":"Vector 2","np":4,"cix":2,"bm":0,"ix":1,"mn":"ADBE Vector Group","hd":false},{"ty":"gr","it":[{"ind":0,"ty":"sh","ix":1,"ks":{"a":0,"k":{"i":[[0,0],[0,0]],"o":[[0,0],[0,0]],"v":[[-57.5,57.5],[-57.5,12.5]],"c":false},"ix":2},"nm":"Path 4","mn":"ADBE Vector Shape - Group","hd":false},{"ty":"tm","s":{"a":0,"k":0,"ix":1},"e":{"a":1,"k":[{"i":{"x":[0.833],"y":[0.833]},"o":{"x":[0.167],"y":[0.167]},"t":17,"s":[0]},{"t":20.25,"s":[100]}],"ix":2},"o":{"a":0,"k":0,"ix":3},"m":1,"ix":2,"nm":"Trim Paths 1","mn":"ADBE Vector Filter - Trim","hd":false},{"ty":"st","c":{"a":0,"k":[0.227,0.2,0.278,1],"ix":3,"x":"var $bm_rt;\n$bm_rt = comp('wired-flat-2547-logo-youtube').layer('control').effect('tertiary')('Color');"},"o":{"a":0,"k":100,"ix":4},"w":{"a":0,"k":7,"ix":5},"lc":2,"lj":2,"bm":0,"nm":".tertiary","mn":"ADBE Vector Graphic - Stroke","hd":false,"cl":"tertiary"},{"ty":"tr","p":{"a":0,"k":[0,0],"ix":2},"a":{"a":0,"k":[0,0],"ix":1},"s":{"a":0,"k":[100,100],"ix":3},"r":{"a":0,"k":0,"ix":6},"o":{"a":0,"k":100,"ix":7},"sk":{"a":0,"k":0,"ix":4},"sa":{"a":0,"k":0,"ix":5},"nm":"Transform"}],"nm":"Vector","np":3,"cix":2,"bm":0,"ix":2,"mn":"ADBE Vector Group","hd":false}],"ip":17,"op":1810,"st":10,"ct":1,"bm":0},{"ddd":0,"ind":13,"ty":4,"nm":"rect","sr":1,"ks":{"o":{"a":0,"k":100,"ix":11},"r":{"a":0,"k":0,"ix":10},"p":{"a":0,"k":[215,285,0],"ix":2,"l":2},"a":{"a":0,"k":[0,0,0],"ix":1,"l":2},"s":{"a":0,"k":[100,100,100],"ix":6,"l":2}},"ao":0,"shapes":[{"ty":"gr","it":[{"ind":0,"ty":"sh","ix":1,"ks":{"a":1,"k":[{"i":{"x":0.404,"y":1},"o":{"x":0.167,"y":0.167},"t":15,"s":[{"i":[[0,0],[-27.5,-0.25],[0,0],[0,-22.091],[0.09,-25.25],[0,0],[-22.091,0],[0,0],[3,28.75],[-0.111,20.5]],"o":[[0,-22.091],[0,0],[-22.091,0],[0,0],[-0.076,21.25],[0,22.091],[0,0],[-72.25,0.75],[0,0],[0.139,-25.75]],"v":[[-49.5,-109.75],[-10,-149.75],[31,-151.75],[-9.75,-110.5],[-14.022,-33.25],[-10.25,29],[32,84.25],[19.75,83.25],[-50.25,29],[-53.418,-34.5]],"c":true}]},{"t":30,"s":[{"i":[[0,0],[-22.091,0],[0,0],[0,-22.091],[0,0],[0,0],[-22.091,0],[0,0],[0,22.091],[0,0]],"o":[[0,-22.091],[0,0],[-22.091,0],[0,0],[0,0],[0,22.091],[0,0],[-22.091,0],[0,0],[0,0]],"v":[[-40,-50],[0,-90],[40,-90],[0,-50],[0,6.436],[0,50],[40,90],[0,90],[-40,50],[-40,8.477]],"c":true}]}],"ix":2},"nm":"Path 1","mn":"ADBE Vector Shape - Group","hd":false},{"ty":"fl","c":{"a":0,"k":[0.949,0.298,0,1],"ix":4,"x":"var $bm_rt;\n$bm_rt = comp('wired-flat-2547-logo-youtube').layer('control').effect('secondary')('Color');"},"o":{"a":0,"k":50,"ix":5},"r":1,"bm":0,"nm":".secondary","mn":"ADBE Vector Graphic - Fill","hd":false,"cl":"secondary"},{"ty":"tr","p":{"a":0,"k":[-120,0],"ix":2},"a":{"a":0,"k":[0,0],"ix":1},"s":{"a":0,"k":[100,100],"ix":3},"r":{"a":0,"k":0,"ix":6},"o":{"a":0,"k":100,"ix":7},"sk":{"a":0,"k":0,"ix":4},"sa":{"a":0,"k":0,"ix":5},"nm":"Transform"}],"nm":"rect-shadow","np":2,"cix":2,"bm":1,"ix":1,"mn":"ADBE Vector Group","hd":false},{"ty":"gr","it":[{"ind":0,"ty":"sh","ix":1,"ks":{"a":1,"k":[{"i":{"x":0.404,"y":1},"o":{"x":0.167,"y":0.167},"t":15,"s":[{"i":[[0,0],[0,-22.091],[0.142,-26.249],[0,0],[-71.75,1.75],[-46.416,-0.092],[0,0],[-4,36.75],[0.121,15.914],[0,0],[52.5,2.25],[36.917,0]],"o":[[-27.75,0],[0,0],[-0.108,20.001],[0,22.091],[0,0],[37.75,0.075],[33,0],[0,0],[-0.212,-27.752],[-3.5,-27.25],[0,0],[-43.083,0]],"v":[[-130,-149.75],[-169.5,-109.75],[-173.176,-34.002],[-170.25,29],[-101.5,83.5],[0.249,84.276],[113.5,82.75],[171.75,37.75],[173.386,-23.243],[171,-107],[111.75,-152],[1,-153.75]],"c":true}]},{"t":30,"s":[{"i":[[0,0],[0,-22.091],[0,0],[0,0],[-22.091,0],[0,0],[0,0],[0,22.091],[0,0],[0,0],[22.091,0],[0,0]],"o":[[-22.091,0],[0,0],[0,0],[0,22.091],[0,0],[0,0],[22.091,0],[0,0],[0,0],[0,-22.091],[0,0],[0,0]],"v":[[-120,-90],[-160,-50],[-160,10.071],[-160,50],[-120,90],[18.468,90],[120,90],[160,50],[160,19.834],[160,-50],[120,-90],[13.848,-90]],"c":true}]}],"ix":2},"nm":"Path 1","mn":"ADBE Vector Shape - Group","hd":false},{"ty":"fl","c":{"a":0,"k":[0.949,0.298,0,1],"ix":4,"x":"var $bm_rt;\n$bm_rt = comp('wired-flat-2547-logo-youtube').layer('control').effect('secondary')('Color');"},"o":{"a":0,"k":100,"ix":5},"r":1,"bm":0,"nm":".secondary","mn":"ADBE Vector Graphic - Fill","hd":false,"cl":"secondary"},{"ty":"tr","p":{"a":0,"k":[0,0],"ix":2},"a":{"a":0,"k":[0,0],"ix":1},"s":{"a":0,"k":[100,100],"ix":3},"r":{"a":0,"k":0,"ix":6},"o":{"a":0,"k":100,"ix":7},"sk":{"a":0,"k":0,"ix":4},"sa":{"a":0,"k":0,"ix":5},"nm":"Transform"}],"nm":"rect","np":2,"cix":2,"bm":0,"ix":2,"mn":"ADBE Vector Group","hd":false}],"ip":15,"op":330,"st":30,"ct":1,"bm":0},{"ddd":0,"ind":14,"ty":3,"nm":"rectangle","sr":1,"ks":{"o":{"a":0,"k":100,"ix":11},"r":{"a":0,"k":0,"ix":10},"p":{"a":0,"k":[215,215,0],"ix":2,"l":2},"a":{"a":0,"k":[0,0,0],"ix":1,"l":2},"s":{"a":0,"k":[100,100,100],"ix":6,"l":2}},"ao":0,"ip":0,"op":16,"st":0,"ct":1,"bm":0},{"ddd":0,"ind":15,"ty":4,"nm":"rectangle 2","sr":1,"ks":{"o":{"a":0,"k":100,"ix":11},"r":{"a":0,"k":0,"ix":10},"p":{"a":0,"k":[215,215,0],"ix":2,"l":2},"a":{"a":0,"k":[0,0,0],"ix":1,"l":2},"s":{"a":0,"k":[100,100,100],"ix":6,"l":2}},"ao":0,"shapes":[{"ty":"gr","it":[{"ind":0,"ty":"sh","ix":1,"ks":{"a":1,"k":[{"i":{"x":0.833,"y":0.833},"o":{"x":0.579,"y":0.004},"t":0,"s":[{"i":[[-30,15],[-81.856,-0.827],[13.496,-6.748],[-30,-15],[-66.938,-0.677],[16.504,8.252]],"o":[[16.504,-8.252],[-66.937,0.677],[-30,15],[13.496,6.748],[-81.857,0.827],[-30,-15]],"v":[[-82.501,-135],[104.999,-146.137],[-37.501,-135],[-37.501,135],[105.001,146.137],[-82.501,135]],"c":true}]},{"i":{"x":0.833,"y":1},"o":{"x":0.167,"y":0.167},"t":15,"s":[{"i":[[-26.442,12.615],[-67.518,1.646],[12.576,-5.986],[-17.684,-25.414],[-14.77,-8.396],[21.308,7.885]],"o":[[22.022,-10.507],[-61.788,0.625],[-25.98,12.365],[8.27,11.885],[-37.27,0.604],[-22.976,-8.502]],"v":[[-73.558,-73.615],[36.268,-82.396],[-33.77,-69.615],[-38.02,129.115],[-12.23,153.146],[-72.558,144.615]],"c":true}]},{"t":30,"s":[{"i":[[-28.307,0.753],[-75.56,-0.046],[12.458,-0.374],[-27.692,-13.846],[-61.789,-0.625],[15.235,7.617]],"o":[[22.308,-0.594],[-61.788,0.038],[-27.692,0.832],[12.458,6.229],[-75.56,0.764],[-27.692,-13.846]],"v":[[-73.558,-53.063],[103.018,-53.666],[-28.27,-53.153],[-31.02,144.615],[100.52,154.896],[-72.558,144.615]],"c":true}]}],"ix":2},"nm":"Path 1","mn":"ADBE Vector Shape - Group","hd":false},{"ty":"fl","c":{"a":0,"k":[0.949,0.298,0,1],"ix":4,"x":"var $bm_rt;\n$bm_rt = comp('wired-flat-2547-logo-youtube').layer('control').effect('secondary')('Color');"},"o":{"a":0,"k":50,"ix":5},"r":1,"bm":0,"nm":".secondary","mn":"ADBE Vector Graphic - Fill","hd":false,"cl":"secondary"},{"ty":"tr","p":{"a":0,"k":[-82.5,0],"ix":2},"a":{"a":0,"k":[0,0],"ix":1},"s":{"a":0,"k":[100,100],"ix":3},"r":{"a":0,"k":0,"ix":6},"o":{"a":0,"k":100,"ix":7},"sk":{"a":0,"k":0,"ix":4},"sa":{"a":0,"k":0,"ix":5},"nm":"Transform"}],"nm":"rectangle-shadow","np":2,"cix":2,"bm":1,"ix":1,"mn":"ADBE Vector Group","hd":false},{"ty":"gr","it":[{"ind":0,"ty":"sh","ix":1,"ks":{"a":1,"k":[{"i":{"x":0.833,"y":0.833},"o":{"x":0.579,"y":0.004},"t":0,"s":[{"i":[[9.496,4.748],[30,-15],[-30,-15],[-75.287,0.029],[-14.942,7.471],[7.524,76.789]],"o":[[-30,-15],[-30,15],[15.058,7.529],[74.711,-0.029],[20.504,-10.252],[-3.484,-35.564]],"v":[[165,-135],[-165,-135],[-165,135],[0.863,146.25],[165,135],[184.471,-67.397]],"c":true}]},{"i":{"x":0.833,"y":1},"o":{"x":0.167,"y":0.167},"t":15,"s":[{"i":[[11.226,6.04],[27.692,-13.846],[-23.052,-8.181],[-69.797,-0.715],[-14.025,7.199],[3.226,61.809]],"o":[[-29.058,-15.635],[-27.692,13.846],[20.808,7.385],[72.88,0.747],[20.192,-10.365],[-1.722,-33]],"v":[[156.558,-72.115],[-156.058,-73.615],[-155.058,144.615],[-0.003,155.02],[154.308,144.365],[173.305,-0.49]],"c":true}]},{"t":30,"s":[{"i":[[9.636,0.387],[27.692,-0.832],[-27.692,-13.846],[-70.519,0.563],[-13.713,5],[5.043,56.485]],"o":[[-25.549,-1.027],[-27.692,0.832],[13.899,6.95],[69.98,-0.559],[15.68,-5.717],[-2.336,-26.16]],"v":[[156.558,-52.973],[-156.058,-53.063],[-155.058,144.615],[0.119,153.441],[153.558,144.365],[174.063,-7.35]],"c":true}]}],"ix":2},"nm":"Path 1","mn":"ADBE Vector Shape - Group","hd":false},{"ty":"fl","c":{"a":0,"k":[0.949,0.298,0,1],"ix":4,"x":"var $bm_rt;\n$bm_rt = comp('wired-flat-2547-logo-youtube').layer('control').effect('secondary')('Color');"},"o":{"a":0,"k":100,"ix":5},"r":1,"bm":0,"nm":".secondary","mn":"ADBE Vector Graphic - Fill","hd":false,"cl":"secondary"},{"ty":"tr","p":{"a":0,"k":[0,0],"ix":2},"a":{"a":0,"k":[0,0],"ix":1},"s":{"a":0,"k":[100,100],"ix":3},"r":{"a":0,"k":0,"ix":6},"o":{"a":0,"k":100,"ix":7},"sk":{"a":0,"k":0,"ix":4},"sa":{"a":0,"k":0,"ix":5},"nm":"Transform"}],"nm":"rectangle","np":2,"cix":2,"bm":0,"ix":2,"mn":"ADBE Vector Group","hd":false}],"ip":0,"op":16,"st":0,"ct":1,"bm":0}]},{"id":"comp_3","nm":"morph-circle","fr":60,"layers":[{"ddd":0,"ind":1,"ty":4,"nm":"mask 2","td":1,"sr":1,"ks":{"o":{"a":0,"k":100,"ix":11},"r":{"a":0,"k":0,"ix":10},"p":{"a":0,"k":[215,215,0],"ix":2,"l":2},"a":{"a":0,"k":[0,0,0],"ix":1,"l":2},"s":{"a":0,"k":[100,100,100],"ix":6,"l":2}},"ao":0,"shapes":[{"ty":"gr","it":[{"ind":0,"ty":"sh","ix":1,"ks":{"a":1,"k":[{"i":{"x":0.311,"y":1},"o":{"x":0.333,"y":0},"t":0,"s":[{"i":[[-1.105,0],[0,-1.105],[1.105,0],[0,1.105]],"o":[[1.105,0],[0,1.105],[-1.105,0],[0,-1.105]],"v":[[0,-1.934],[2,0.066],[0,2.066],[-2,0.066]],"c":true}]},{"t":30,"s":[{"i":[[-92.508,0],[0,-92.508],[92.508,0],[0,92.508]],"o":[[92.508,0],[0,92.508],[-92.508,0],[0,-92.508]],"v":[[0,-167.5],[167.5,0],[0,167.5],[-167.5,0]],"c":true}]}],"ix":2},"nm":"Path 1","mn":"ADBE Vector Shape - Group","hd":false},{"ty":"fl","c":{"a":0,"k":[0.949019667682,0.298039215686,0,1],"ix":4},"o":{"a":0,"k":100,"ix":5},"r":1,"bm":0,"nm":".primary","mn":"ADBE Vector Graphic - Fill","hd":false,"cl":"primary"},{"ty":"tr","p":{"a":0,"k":[0,0],"ix":2},"a":{"a":0,"k":[0,0],"ix":1},"s":{"a":0,"k":[100,100],"ix":3},"r":{"a":0,"k":0,"ix":6},"o":{"a":0,"k":100,"ix":7},"sk":{"a":0,"k":0,"ix":4},"sa":{"a":0,"k":0,"ix":5},"nm":"Transform"}],"nm":"circle","np":2,"cix":2,"bm":0,"ix":1,"mn":"ADBE Vector Group","hd":false}],"ip":6,"op":300,"st":0,"ct":1,"bm":0},{"ddd":0,"ind":2,"ty":0,"nm":"rewers","tt":1,"tp":1,"refId":"comp_4","sr":1,"ks":{"o":{"a":0,"k":100,"ix":11},"r":{"a":0,"k":0,"ix":10},"p":{"a":0,"k":[215,215,0],"ix":2,"l":2},"a":{"a":0,"k":[215,215,0],"ix":1,"l":2},"s":{"a":0,"k":[100,100,100],"ix":6,"l":2}},"ao":0,"w":430,"h":430,"ip":0,"op":1800,"st":0,"bm":0},{"ddd":0,"ind":3,"ty":4,"nm":"mask","td":1,"sr":1,"ks":{"o":{"a":0,"k":100,"ix":11},"r":{"a":0,"k":0,"ix":10},"p":{"a":0,"k":[215,215,0],"ix":2,"l":2},"a":{"a":0,"k":[0,0,0],"ix":1,"l":2},"s":{"a":0,"k":[100,100,100],"ix":6,"l":2}},"ao":0,"shapes":[{"ty":"gr","it":[{"ind":0,"ty":"sh","ix":1,"ks":{"a":1,"k":[{"i":{"x":0.311,"y":1},"o":{"x":0.333,"y":0},"t":0,"s":[{"i":[[-1.105,0],[0,-1.105],[1.105,0],[0,1.105]],"o":[[1.105,0],[0,1.105],[-1.105,0],[0,-1.105]],"v":[[0,-1.934],[2,0.066],[0,2.066],[-2,0.066]],"c":true}]},{"t":30,"s":[{"i":[[-92.508,0],[0,-92.508],[92.508,0],[0,92.508]],"o":[[92.508,0],[0,92.508],[-92.508,0],[0,-92.508]],"v":[[0,-167.5],[167.5,0],[0,167.5],[-167.5,0]],"c":true}]}],"ix":2},"nm":"Path 1","mn":"ADBE Vector Shape - Group","hd":false},{"ty":"fl","c":{"a":0,"k":[0.949019667682,0.298039215686,0,1],"ix":4},"o":{"a":0,"k":100,"ix":5},"r":1,"bm":0,"nm":".primary","mn":"ADBE Vector Graphic - Fill","hd":false,"cl":"primary"},{"ty":"tr","p":{"a":0,"k":[0,0],"ix":2},"a":{"a":0,"k":[0,0],"ix":1},"s":{"a":0,"k":[100,100],"ix":3},"r":{"a":0,"k":0,"ix":6},"o":{"a":0,"k":100,"ix":7},"sk":{"a":0,"k":0,"ix":4},"sa":{"a":0,"k":0,"ix":5},"nm":"Transform"}],"nm":"circle","np":2,"cix":2,"bm":0,"ix":1,"mn":"ADBE Vector Group","hd":false}],"ip":6,"op":300,"st":0,"ct":1,"bm":0},{"ddd":0,"ind":4,"ty":0,"nm":"awers","tt":2,"tp":3,"refId":"comp_5","sr":1,"ks":{"o":{"a":0,"k":100,"ix":11},"r":{"a":0,"k":0,"ix":10},"p":{"a":0,"k":[215,215,0],"ix":2,"l":2},"a":{"a":0,"k":[215,215,0],"ix":1,"l":2},"s":{"a":0,"k":[100,100,100],"ix":6,"l":2}},"ao":0,"w":430,"h":430,"ip":0,"op":1800,"st":0,"bm":0},{"ddd":0,"ind":5,"ty":4,"nm":"circle 2","sr":1,"ks":{"o":{"a":0,"k":100,"ix":11},"r":{"a":0,"k":0,"ix":10},"p":{"a":0,"k":[215,215,0],"ix":2,"l":2},"a":{"a":0,"k":[0,0,0],"ix":1,"l":2},"s":{"a":0,"k":[100,100,100],"ix":6,"l":2}},"ao":0,"shapes":[{"ty":"gr","it":[{"ind":0,"ty":"sh","ix":1,"ks":{"a":1,"k":[{"i":{"x":0.311,"y":1},"o":{"x":0.333,"y":0},"t":0,"s":[{"i":[[-1.105,0],[-0.182,0.054],[0.361,0],[0,1.105],[-0.825,0.246],[0,-0.744]],"o":[[0.199,0],[-0.292,0.167],[-1.105,0],[0,-0.905],[-0.603,0.345],[0,1.105]],"v":[[135.544,-51.236],[136.118,-51.319],[135.126,-51.057],[133.126,-53.057],[134.553,-54.974],[133.544,-53.236]],"c":true}]},{"t":30,"s":[{"i":[[-92.508,0],[-15.208,4.542],[30.203,0],[0,92.508],[-69.112,20.64],[0,-62.305]],"o":[[16.684,0],[-24.468,13.987],[-92.508,0],[0,-75.823],[-50.475,28.854],[0,92.508]],"v":[[170.247,99.509],[218.253,92.528],[135.247,114.51],[-32.253,-52.99],[87.24,-213.51],[2.747,-67.991]],"c":true}]}],"ix":2},"nm":"Path 1","mn":"ADBE Vector Shape - Group","hd":false},{"ty":"fl","c":{"a":0,"k":[0.949,0.298,0,1],"ix":4,"x":"var $bm_rt;\n$bm_rt = comp('wired-flat-2547-logo-youtube').layer('control').effect('secondary')('Color');"},"o":{"a":0,"k":50,"ix":5},"r":1,"bm":0,"nm":".secondary","mn":"ADBE Vector Graphic - Fill","hd":false,"cl":"secondary"},{"ty":"tr","p":{"a":0,"k":[-135.125,53.125],"ix":2},"a":{"a":0,"k":[0,0],"ix":1},"s":{"a":0,"k":[100,100],"ix":3},"r":{"a":0,"k":0,"ix":6},"o":{"a":0,"k":100,"ix":7},"sk":{"a":0,"k":0,"ix":4},"sa":{"a":0,"k":0,"ix":5},"nm":"Transform"}],"nm":"circle-shadow","np":2,"cix":2,"bm":1,"ix":1,"mn":"ADBE Vector Group","hd":false},{"ty":"gr","it":[{"ind":0,"ty":"sh","ix":1,"ks":{"a":1,"k":[{"i":{"x":0.311,"y":1},"o":{"x":0.333,"y":0},"t":0,"s":[{"i":[[-1.105,0],[0,-1.105],[1.105,0],[0,1.105]],"o":[[1.105,0],[0,1.105],[-1.105,0],[0,-1.105]],"v":[[0,-1.934],[2,0.066],[0,2.066],[-2,0.066]],"c":true}]},{"t":30,"s":[{"i":[[-92.508,0],[0,-92.508],[92.508,0],[0,92.508]],"o":[[92.508,0],[0,92.508],[-92.508,0],[0,-92.508]],"v":[[0,-167.5],[167.5,0],[0,167.5],[-167.5,0]],"c":true}]}],"ix":2},"nm":"Path 1","mn":"ADBE Vector Shape - Group","hd":false},{"ty":"fl","c":{"a":0,"k":[0.949,0.298,0,1],"ix":4,"x":"var $bm_rt;\n$bm_rt = comp('wired-flat-2547-logo-youtube').layer('control').effect('secondary')('Color');"},"o":{"a":0,"k":100,"ix":5},"r":1,"bm":0,"nm":".secondary","mn":"ADBE Vector Graphic - Fill","hd":false,"cl":"secondary"},{"ty":"tr","p":{"a":0,"k":[0,0],"ix":2},"a":{"a":0,"k":[0,0],"ix":1},"s":{"a":0,"k":[100,100],"ix":3},"r":{"a":0,"k":0,"ix":6},"o":{"a":0,"k":100,"ix":7},"sk":{"a":0,"k":0,"ix":4},"sa":{"a":0,"k":0,"ix":5},"nm":"Transform"}],"nm":"circle","np":2,"cix":2,"bm":0,"ix":2,"mn":"ADBE Vector Group","hd":false}],"ip":0,"op":300,"st":0,"ct":1,"bm":0}]},{"id":"comp_4","nm":"rewers","fr":60,"layers":[{"ddd":0,"ind":2,"ty":4,"nm":"mask 2","parent":10,"td":1,"sr":1,"ks":{"o":{"a":0,"k":100,"ix":11},"r":{"a":0,"k":0,"ix":10},"p":{"a":0,"k":[0,0,0],"ix":2,"l":2},"a":{"a":0,"k":[0,0,0],"ix":1,"l":2},"s":{"a":0,"k":[100,100,100],"ix":6,"l":2}},"ao":0,"shapes":[{"ty":"gr","it":[{"ind":0,"ty":"sh","ix":1,"ks":{"a":0,"k":{"i":[[30,15],[30,-15],[-30,-15],[-30,15]],"o":[[-30,-15],[-30,15],[30,15],[30,-15]],"v":[[165,-135],[-165,-135],[-165,135],[165,135]],"c":true},"ix":2},"nm":"Path 1","mn":"ADBE Vector Shape - Group","hd":false},{"ty":"fl","c":{"a":0,"k":[1,0,0,1],"ix":4},"o":{"a":0,"k":100,"ix":5},"r":1,"bm":0,"nm":"Fill 1","mn":"ADBE Vector Graphic - Fill","hd":false},{"ty":"tr","p":{"a":0,"k":[0,0],"ix":2},"a":{"a":0,"k":[0,0],"ix":1},"s":{"a":0,"k":[100,100],"ix":3},"r":{"a":0,"k":0,"ix":6},"o":{"a":0,"k":100,"ix":7},"sk":{"a":0,"k":0,"ix":4},"sa":{"a":0,"k":0,"ix":5},"nm":"Transform"}],"nm":"rectangle","np":2,"cix":2,"bm":0,"ix":1,"mn":"ADBE Vector Group","hd":false}],"ip":0,"op":171,"st":0,"ct":1,"bm":0},{"ddd":0,"ind":3,"ty":4,"nm":"triangle 6","parent":4,"tt":1,"tp":2,"sr":1,"ks":{"o":{"a":0,"k":100,"ix":11},"r":{"a":0,"k":-540,"ix":10},"p":{"a":0,"k":[1.196,0,0],"ix":2,"l":2},"a":{"a":0,"k":[0,0,0],"ix":1,"l":2},"s":{"a":0,"k":[100,100,100],"ix":6,"l":2}},"ao":0,"shapes":[{"ty":"gr","it":[{"ind":0,"ty":"sh","ix":1,"ks":{"a":0,"k":{"i":[[0,0],[0,0],[0,0],[0,2.399],[0,0],[-1.993,-1.335]],"o":[[0,0],[0,0],[-1.993,1.335],[0,0],[0,-2.399],[0,0]],"v":[[15,-56.913],[15,56.913],[-10.331,73.874],[-15,71.381],[-15,-71.381],[-10.331,-73.874]],"c":true},"ix":2},"nm":"Path 1","mn":"ADBE Vector Shape - Group","hd":false},{"ty":"fl","c":{"a":0,"k":[0.949,0.298,0,1],"ix":4,"x":"var $bm_rt;\n$bm_rt = comp('wired-flat-2547-logo-youtube').layer('control').effect('secondary')('Color');"},"o":{"a":0,"k":50,"ix":5},"r":1,"bm":0,"nm":".secondary","mn":"ADBE Vector Graphic - Fill","hd":false,"cl":"secondary"},{"ty":"tr","p":{"a":0,"k":[-41.375,0],"ix":2},"a":{"a":0,"k":[0,0],"ix":1},"s":{"a":0,"k":[100,100],"ix":3},"r":{"a":0,"k":0,"ix":6},"o":{"a":0,"k":100,"ix":7},"sk":{"a":0,"k":0,"ix":4},"sa":{"a":0,"k":0,"ix":5},"nm":"Transform"}],"nm":"triangle-shadow","np":2,"cix":2,"bm":1,"ix":1,"mn":"ADBE Vector Group","hd":false},{"ty":"gr","it":[{"ind":0,"ty":"sh","ix":1,"ks":{"a":0,"k":{"i":[[0,0],[1.775,1.188],[0,0],[0,-2.399],[0,0],[-1.993,1.335]],"o":[[1.775,-1.188],[0,0],[-1.993,-1.335],[0,0],[0,2.399],[0,0]],"v":[[54.973,2.493],[54.973,-2.493],[-51.635,-73.874],[-56.304,-71.381],[-56.304,71.381],[-51.635,73.874]],"c":true},"ix":2},"nm":"Path 1","mn":"ADBE Vector Shape - Group","hd":false},{"ty":"rd","nm":"Round Corners 1","r":{"a":0,"k":3,"ix":1},"ix":2,"mn":"ADBE Vector Filter - RC","hd":false},{"ty":"fl","c":{"a":0,"k":[0.949,0.298,0,1],"ix":4,"x":"var $bm_rt;\n$bm_rt = comp('wired-flat-2547-logo-youtube').layer('control').effect('secondary')('Color');"},"o":{"a":0,"k":100,"ix":5},"r":1,"bm":0,"nm":".secondary","mn":"ADBE Vector Graphic - Fill","hd":false,"cl":"secondary"},{"ty":"tr","p":{"a":0,"k":[0,0],"ix":2},"a":{"a":0,"k":[0,0],"ix":1},"s":{"a":0,"k":[100,100],"ix":3},"r":{"a":0,"k":0,"ix":6},"o":{"a":0,"k":100,"ix":7},"sk":{"a":0,"k":0,"ix":4},"sa":{"a":0,"k":0,"ix":5},"nm":"Transform"}],"nm":"triangle","np":3,"cix":2,"bm":0,"ix":2,"mn":"ADBE Vector Group","hd":false}],"ip":0,"op":300,"st":0,"ct":1,"bm":0},{"ddd":0,"ind":4,"ty":3,"nm":"triangle 2","parent":10,"sr":1,"ks":{"o":{"a":0,"k":100,"ix":11},"r":{"a":0,"k":0,"ix":10},"p":{"a":1,"k":[{"i":{"x":0.385,"y":1},"o":{"x":0.167,"y":0.167},"t":2,"s":[-245.5,0,0],"to":[0,0,0],"ti":[0,0,0]},{"i":{"x":0.397,"y":1},"o":{"x":0.46,"y":0},"t":13,"s":[54.5,0,0],"to":[0,0,0],"ti":[0,0,0]},{"t":30,"s":[14.5,0,0]}],"ix":2,"l":2},"a":{"a":0,"k":[0,0,0],"ix":1,"l":2},"s":{"a":0,"k":[-100,-100,100],"ix":6,"l":2}},"ao":0,"ip":0,"op":10,"st":0,"ct":1,"bm":0},{"ddd":0,"ind":5,"ty":4,"nm":"mask","parent":10,"td":1,"sr":1,"ks":{"o":{"a":0,"k":100,"ix":11},"r":{"a":0,"k":0,"ix":10},"p":{"a":0,"k":[0,0,0],"ix":2,"l":2},"a":{"a":0,"k":[0,0,0],"ix":1,"l":2},"s":{"a":0,"k":[100,100,100],"ix":6,"l":2}},"ao":0,"shapes":[{"ty":"gr","it":[{"ind":0,"ty":"sh","ix":1,"ks":{"a":0,"k":{"i":[[30,15],[30,-15],[-30,-15],[-30,15]],"o":[[-30,-15],[-30,15],[30,15],[30,-15]],"v":[[165,-135],[-165,-135],[-165,135],[165,135]],"c":true},"ix":2},"nm":"Path 1","mn":"ADBE Vector Shape - Group","hd":false},{"ty":"fl","c":{"a":0,"k":[1,0,0,1],"ix":4},"o":{"a":0,"k":100,"ix":5},"r":1,"bm":0,"nm":"Fill 1","mn":"ADBE Vector Graphic - Fill","hd":false},{"ty":"tr","p":{"a":0,"k":[0,0],"ix":2},"a":{"a":0,"k":[0,0],"ix":1},"s":{"a":0,"k":[100,100],"ix":3},"r":{"a":0,"k":0,"ix":6},"o":{"a":0,"k":100,"ix":7},"sk":{"a":0,"k":0,"ix":4},"sa":{"a":0,"k":0,"ix":5},"nm":"Transform"}],"nm":"rectangle","np":2,"cix":2,"bm":0,"ix":1,"mn":"ADBE Vector Group","hd":false}],"ip":4,"op":1800,"st":0,"ct":1,"bm":0},{"ddd":0,"ind":7,"ty":3,"nm":"triangle","parent":10,"sr":1,"ks":{"o":{"a":0,"k":100,"ix":11},"r":{"a":0,"k":0,"ix":10},"p":{"a":1,"k":[{"i":{"x":0.833,"y":0.833},"o":{"x":0.333,"y":0},"t":0,"s":[14.5,0,0],"to":[0,0,0],"ti":[0,0,0]},{"t":7,"s":[254.5,0,0]}],"ix":2,"l":2},"a":{"a":0,"k":[0,0,0],"ix":1,"l":2},"s":{"a":0,"k":[-100,-100,100],"ix":6,"l":2}},"ao":0,"ip":0,"op":4,"st":0,"ct":1,"bm":0},{"ddd":0,"ind":8,"ty":4,"nm":"mask 3","parent":10,"td":1,"sr":1,"ks":{"o":{"a":0,"k":100,"ix":11},"r":{"a":0,"k":0,"ix":10},"p":{"a":0,"k":[0,0,0],"ix":2,"l":2},"a":{"a":0,"k":[0,0,0],"ix":1,"l":2},"s":{"a":0,"k":[100,100,100],"ix":6,"l":2}},"ao":0,"shapes":[{"ty":"gr","it":[{"ind":0,"ty":"sh","ix":1,"ks":{"a":0,"k":{"i":[[30,15],[30,-15],[-30,-15],[-30,15]],"o":[[-30,-15],[-30,15],[30,15],[30,-15]],"v":[[165,-135],[-165,-135],[-165,135],[165,135]],"c":true},"ix":2},"nm":"Path 1","mn":"ADBE Vector Shape - Group","hd":false},{"ty":"fl","c":{"a":0,"k":[1,0,0,1],"ix":4},"o":{"a":0,"k":100,"ix":5},"r":1,"bm":0,"nm":"Fill 1","mn":"ADBE Vector Graphic - Fill","hd":false},{"ty":"tr","p":{"a":0,"k":[0,0],"ix":2},"a":{"a":0,"k":[0,0],"ix":1},"s":{"a":0,"k":[100,100],"ix":3},"r":{"a":0,"k":0,"ix":6},"o":{"a":0,"k":100,"ix":7},"sk":{"a":0,"k":0,"ix":4},"sa":{"a":0,"k":0,"ix":5},"nm":"Transform"}],"nm":"rectangle","np":2,"cix":2,"bm":0,"ix":1,"mn":"ADBE Vector Group","hd":false}],"ip":0,"op":1800,"st":0,"ct":1,"bm":0},{"ddd":0,"ind":9,"ty":4,"nm":"triangle 5","parent":7,"tt":1,"tp":8,"sr":1,"ks":{"o":{"a":0,"k":100,"ix":11},"r":{"a":0,"k":-540,"ix":10},"p":{"a":0,"k":[1.196,0,0],"ix":2,"l":2},"a":{"a":0,"k":[0,0,0],"ix":1,"l":2},"s":{"a":0,"k":[100,100,100],"ix":6,"l":2}},"ao":0,"shapes":[{"ty":"gr","it":[{"ind":0,"ty":"sh","ix":1,"ks":{"a":0,"k":{"i":[[0,0],[0,0],[0,0],[0,2.399],[0,0],[-1.993,-1.335]],"o":[[0,0],[0,0],[-1.993,1.335],[0,0],[0,-2.399],[0,0]],"v":[[15,-56.913],[15,56.913],[-10.331,73.874],[-15,71.381],[-15,-71.381],[-10.331,-73.874]],"c":true},"ix":2},"nm":"Path 1","mn":"ADBE Vector Shape - Group","hd":false},{"ty":"fl","c":{"a":0,"k":[0.949,0.298,0,1],"ix":4,"x":"var $bm_rt;\n$bm_rt = comp('wired-flat-2547-logo-youtube').layer('control').effect('secondary')('Color');"},"o":{"a":0,"k":50,"ix":5},"r":1,"bm":0,"nm":".secondary","mn":"ADBE Vector Graphic - Fill","hd":false,"cl":"secondary"},{"ty":"tr","p":{"a":0,"k":[-41.375,0],"ix":2},"a":{"a":0,"k":[0,0],"ix":1},"s":{"a":0,"k":[100,100],"ix":3},"r":{"a":0,"k":0,"ix":6},"o":{"a":0,"k":100,"ix":7},"sk":{"a":0,"k":0,"ix":4},"sa":{"a":0,"k":0,"ix":5},"nm":"Transform"}],"nm":"triangle-shadow","np":2,"cix":2,"bm":1,"ix":1,"mn":"ADBE Vector Group","hd":false},{"ty":"gr","it":[{"ind":0,"ty":"sh","ix":1,"ks":{"a":0,"k":{"i":[[0,0],[1.775,1.188],[0,0],[0,-2.399],[0,0],[-1.993,1.335]],"o":[[1.775,-1.188],[0,0],[-1.993,-1.335],[0,0],[0,2.399],[0,0]],"v":[[54.973,2.493],[54.973,-2.493],[-51.635,-73.874],[-56.304,-71.381],[-56.304,71.381],[-51.635,73.874]],"c":true},"ix":2},"nm":"Path 1","mn":"ADBE Vector Shape - Group","hd":false},{"ty":"rd","nm":"Round Corners 1","r":{"a":0,"k":3,"ix":1},"ix":2,"mn":"ADBE Vector Filter - RC","hd":false},{"ty":"fl","c":{"a":0,"k":[0.949,0.298,0,1],"ix":4,"x":"var $bm_rt;\n$bm_rt = comp('wired-flat-2547-logo-youtube').layer('control').effect('secondary')('Color');"},"o":{"a":0,"k":100,"ix":5},"r":1,"bm":0,"nm":".secondary","mn":"ADBE Vector Graphic - Fill","hd":false,"cl":"secondary"},{"ty":"tr","p":{"a":0,"k":[0,0],"ix":2},"a":{"a":0,"k":[0,0],"ix":1},"s":{"a":0,"k":[100,100],"ix":3},"r":{"a":0,"k":0,"ix":6},"o":{"a":0,"k":100,"ix":7},"sk":{"a":0,"k":0,"ix":4},"sa":{"a":0,"k":0,"ix":5},"nm":"Transform"}],"nm":"triangle","np":3,"cix":2,"bm":0,"ix":2,"mn":"ADBE Vector Group","hd":false}],"ip":0,"op":300,"st":0,"ct":1,"bm":0},{"ddd":0,"ind":10,"ty":3,"nm":"rectangle","sr":1,"ks":{"o":{"a":0,"k":100,"ix":11},"r":{"a":0,"k":0,"ix":10},"p":{"a":0,"k":[215,215,0],"ix":2,"l":2},"a":{"a":0,"k":[0,0,0],"ix":1,"l":2},"s":{"a":1,"k":[{"i":{"x":[0.18,0.18,0.18],"y":[1,1,1]},"o":{"x":[0.42,0.42,0.42],"y":[0,0,0]},"t":0,"s":[100,100,100]},{"t":30,"s":[61.3,61.3,100]}],"ix":6,"l":2}},"ao":0,"ip":0,"op":1800,"st":0,"ct":1,"bm":0},{"ddd":0,"ind":11,"ty":4,"nm":"rectangle 2","parent":10,"sr":1,"ks":{"o":{"a":0,"k":100,"ix":11},"r":{"a":0,"k":0,"ix":10},"p":{"a":0,"k":[0,0,0],"ix":2,"l":2},"a":{"a":0,"k":[0,0,0],"ix":1,"l":2},"s":{"a":0,"k":[100,100,100],"ix":6,"l":2}},"ao":0,"shapes":[{"ty":"gr","it":[{"ind":0,"ty":"sh","ix":1,"ks":{"a":0,"k":{"i":[[-30,15],[-81.856,-0.827],[13.496,-6.748],[-30,-15],[-66.938,-0.677],[16.504,8.252]],"o":[[16.504,-8.252],[-66.937,0.677],[-30,15],[13.496,6.748],[-81.857,0.827],[-30,-15]],"v":[[-82.501,-135],[104.999,-146.137],[-37.501,-135],[-37.501,135],[105.001,146.137],[-82.501,135]],"c":true},"ix":2},"nm":"Path 1","mn":"ADBE Vector Shape - Group","hd":false},{"ty":"fl","c":{"a":0,"k":[0.922,0.902,0.937,1],"ix":4,"x":"var $bm_rt;\n$bm_rt = comp('wired-flat-2547-logo-youtube').layer('control').effect('primary')('Color');"},"o":{"a":0,"k":50,"ix":5},"r":1,"bm":0,"nm":".primary","mn":"ADBE Vector Graphic - Fill","hd":false,"cl":"primary"},{"ty":"tr","p":{"a":0,"k":[-82.5,0],"ix":2},"a":{"a":0,"k":[0,0],"ix":1},"s":{"a":0,"k":[100,100],"ix":3},"r":{"a":0,"k":0,"ix":6},"o":{"a":0,"k":100,"ix":7},"sk":{"a":0,"k":0,"ix":4},"sa":{"a":0,"k":0,"ix":5},"nm":"Transform"}],"nm":"rectangle-shadow","np":2,"cix":2,"bm":1,"ix":1,"mn":"ADBE Vector Group","hd":false},{"ty":"gr","it":[{"ind":0,"ty":"sh","ix":1,"ks":{"a":0,"k":{"i":[[30,15],[30,-15],[-30,-15],[-30,15]],"o":[[-30,-15],[-30,15],[30,15],[30,-15]],"v":[[165,-135],[-165,-135],[-165,135],[165,135]],"c":true},"ix":2},"nm":"Path 1","mn":"ADBE Vector Shape - Group","hd":false},{"ty":"fl","c":{"a":0,"k":[0.922,0.902,0.937,1],"ix":4,"x":"var $bm_rt;\n$bm_rt = comp('wired-flat-2547-logo-youtube').layer('control').effect('primary')('Color');"},"o":{"a":0,"k":100,"ix":5},"r":1,"bm":0,"nm":".primary","mn":"ADBE Vector Graphic - Fill","hd":false,"cl":"primary"},{"ty":"tr","p":{"a":0,"k":[0,0],"ix":2},"a":{"a":0,"k":[0,0],"ix":1},"s":{"a":0,"k":[100,100],"ix":3},"r":{"a":0,"k":0,"ix":6},"o":{"a":0,"k":100,"ix":7},"sk":{"a":0,"k":0,"ix":4},"sa":{"a":0,"k":0,"ix":5},"nm":"Transform"}],"nm":"rectangle","np":2,"cix":2,"bm":0,"ix":2,"mn":"ADBE Vector Group","hd":false}],"ip":0,"op":300,"st":0,"ct":1,"bm":0}]},{"id":"comp_5","nm":"awers","fr":60,"layers":[{"ddd":0,"ind":2,"ty":4,"nm":"mask 2","parent":10,"td":1,"sr":1,"ks":{"o":{"a":0,"k":100,"ix":11},"r":{"a":0,"k":0,"ix":10},"p":{"a":0,"k":[0,0,0],"ix":2,"l":2},"a":{"a":0,"k":[0,0,0],"ix":1,"l":2},"s":{"a":0,"k":[100,100,100],"ix":6,"l":2}},"ao":0,"shapes":[{"ty":"gr","it":[{"ind":0,"ty":"sh","ix":1,"ks":{"a":0,"k":{"i":[[30,15],[30,-15],[-30,-15],[-30,15]],"o":[[-30,-15],[-30,15],[30,15],[30,-15]],"v":[[165,-135],[-165,-135],[-165,135],[165,135]],"c":true},"ix":2},"nm":"Path 1","mn":"ADBE Vector Shape - Group","hd":false},{"ty":"fl","c":{"a":0,"k":[1,0,0,1],"ix":4},"o":{"a":0,"k":100,"ix":5},"r":1,"bm":0,"nm":"Fill 1","mn":"ADBE Vector Graphic - Fill","hd":false},{"ty":"tr","p":{"a":0,"k":[0,0],"ix":2},"a":{"a":0,"k":[0,0],"ix":1},"s":{"a":0,"k":[100,100],"ix":3},"r":{"a":0,"k":0,"ix":6},"o":{"a":0,"k":100,"ix":7},"sk":{"a":0,"k":0,"ix":4},"sa":{"a":0,"k":0,"ix":5},"nm":"Transform"}],"nm":"rectangle","np":2,"cix":2,"bm":0,"ix":1,"mn":"ADBE Vector Group","hd":false}],"ip":0,"op":172,"st":0,"ct":1,"bm":0},{"ddd":0,"ind":3,"ty":4,"nm":"triangle 6","parent":4,"tt":1,"tp":2,"sr":1,"ks":{"o":{"a":0,"k":100,"ix":11},"r":{"a":0,"k":-540,"ix":10},"p":{"a":0,"k":[1.196,0,0],"ix":2,"l":2},"a":{"a":0,"k":[0,0,0],"ix":1,"l":2},"s":{"a":0,"k":[100,100,100],"ix":6,"l":2}},"ao":0,"shapes":[{"ty":"gr","it":[{"ind":0,"ty":"sh","ix":1,"ks":{"a":0,"k":{"i":[[0,0],[0,0],[0,0],[0,2.399],[0,0],[-1.993,-1.335]],"o":[[0,0],[0,0],[-1.993,1.335],[0,0],[0,-2.399],[0,0]],"v":[[15,-56.913],[15,56.913],[-10.331,73.874],[-15,71.381],[-15,-71.381],[-10.331,-73.874]],"c":true},"ix":2},"nm":"Path 1","mn":"ADBE Vector Shape - Group","hd":false},{"ty":"fl","c":{"a":0,"k":[0.922,0.902,0.937,1],"ix":4,"x":"var $bm_rt;\n$bm_rt = comp('wired-flat-2547-logo-youtube').layer('control').effect('primary')('Color');"},"o":{"a":0,"k":50,"ix":5},"r":1,"bm":0,"nm":".primary","mn":"ADBE Vector Graphic - Fill","hd":false,"cl":"primary"},{"ty":"tr","p":{"a":0,"k":[-41.375,0],"ix":2},"a":{"a":0,"k":[0,0],"ix":1},"s":{"a":0,"k":[100,100],"ix":3},"r":{"a":0,"k":0,"ix":6},"o":{"a":0,"k":100,"ix":7},"sk":{"a":0,"k":0,"ix":4},"sa":{"a":0,"k":0,"ix":5},"nm":"Transform"}],"nm":"triangle-shadow","np":2,"cix":2,"bm":1,"ix":1,"mn":"ADBE Vector Group","hd":false},{"ty":"gr","it":[{"ind":0,"ty":"sh","ix":1,"ks":{"a":0,"k":{"i":[[0,0],[1.775,1.188],[0,0],[0,-2.399],[0,0],[-1.993,1.335]],"o":[[1.775,-1.188],[0,0],[-1.993,-1.335],[0,0],[0,2.399],[0,0]],"v":[[54.973,2.493],[54.973,-2.493],[-51.635,-73.874],[-56.304,-71.381],[-56.304,71.381],[-51.635,73.874]],"c":true},"ix":2},"nm":"Path 1","mn":"ADBE Vector Shape - Group","hd":false},{"ty":"rd","nm":"Round Corners 1","r":{"a":0,"k":3,"ix":1},"ix":2,"mn":"ADBE Vector Filter - RC","hd":false},{"ty":"fl","c":{"a":0,"k":[0.922,0.902,0.937,1],"ix":4,"x":"var $bm_rt;\n$bm_rt = comp('wired-flat-2547-logo-youtube').layer('control').effect('primary')('Color');"},"o":{"a":0,"k":100,"ix":5},"r":1,"bm":0,"nm":".primary","mn":"ADBE Vector Graphic - Fill","hd":false,"cl":"primary"},{"ty":"tr","p":{"a":0,"k":[0,0],"ix":2},"a":{"a":0,"k":[0,0],"ix":1},"s":{"a":0,"k":[100,100],"ix":3},"r":{"a":0,"k":0,"ix":6},"o":{"a":0,"k":100,"ix":7},"sk":{"a":0,"k":0,"ix":4},"sa":{"a":0,"k":0,"ix":5},"nm":"Transform"}],"nm":"triangle","np":3,"cix":2,"bm":0,"ix":2,"mn":"ADBE Vector Group","hd":false}],"ip":0,"op":300,"st":0,"ct":1,"bm":0},{"ddd":0,"ind":4,"ty":3,"nm":"triangle 2","parent":10,"sr":1,"ks":{"o":{"a":0,"k":100,"ix":11},"r":{"a":0,"k":0,"ix":10},"p":{"a":1,"k":[{"i":{"x":0.385,"y":1},"o":{"x":0.167,"y":0.167},"t":2,"s":[-245.5,0,0],"to":[0,0,0],"ti":[0,0,0]},{"i":{"x":0.397,"y":1},"o":{"x":0.46,"y":0},"t":13,"s":[54.5,0,0],"to":[0,0,0],"ti":[0,0,0]},{"t":30,"s":[14.5,0,0]}],"ix":2,"l":2},"a":{"a":0,"k":[0,0,0],"ix":1,"l":2},"s":{"a":0,"k":[-100,-100,100],"ix":6,"l":2}},"ao":0,"ip":0,"op":10,"st":0,"ct":1,"bm":0},{"ddd":0,"ind":5,"ty":4,"nm":"mask","parent":10,"td":1,"sr":1,"ks":{"o":{"a":0,"k":100,"ix":11},"r":{"a":0,"k":0,"ix":10},"p":{"a":0,"k":[0,0,0],"ix":2,"l":2},"a":{"a":0,"k":[0,0,0],"ix":1,"l":2},"s":{"a":0,"k":[100,100,100],"ix":6,"l":2}},"ao":0,"shapes":[{"ty":"gr","it":[{"ind":0,"ty":"sh","ix":1,"ks":{"a":0,"k":{"i":[[30,15],[30,-15],[-30,-15],[-30,15]],"o":[[-30,-15],[-30,15],[30,15],[30,-15]],"v":[[165,-135],[-165,-135],[-165,135],[165,135]],"c":true},"ix":2},"nm":"Path 1","mn":"ADBE Vector Shape - Group","hd":false},{"ty":"fl","c":{"a":0,"k":[1,0,0,1],"ix":4},"o":{"a":0,"k":100,"ix":5},"r":1,"bm":0,"nm":"Fill 1","mn":"ADBE Vector Graphic - Fill","hd":false},{"ty":"tr","p":{"a":0,"k":[0,0],"ix":2},"a":{"a":0,"k":[0,0],"ix":1},"s":{"a":0,"k":[100,100],"ix":3},"r":{"a":0,"k":0,"ix":6},"o":{"a":0,"k":100,"ix":7},"sk":{"a":0,"k":0,"ix":4},"sa":{"a":0,"k":0,"ix":5},"nm":"Transform"}],"nm":"rectangle","np":2,"cix":2,"bm":0,"ix":1,"mn":"ADBE Vector Group","hd":false}],"ip":4,"op":1800,"st":0,"ct":1,"bm":0},{"ddd":0,"ind":7,"ty":3,"nm":"triangle","parent":10,"sr":1,"ks":{"o":{"a":0,"k":100,"ix":11},"r":{"a":0,"k":0,"ix":10},"p":{"a":1,"k":[{"i":{"x":0.833,"y":0.833},"o":{"x":0.333,"y":0},"t":0,"s":[14.5,0,0],"to":[0,0,0],"ti":[0,0,0]},{"t":7,"s":[254.5,0,0]}],"ix":2,"l":2},"a":{"a":0,"k":[0,0,0],"ix":1,"l":2},"s":{"a":0,"k":[-100,-100,100],"ix":6,"l":2}},"ao":0,"ip":0,"op":4,"st":0,"ct":1,"bm":0},{"ddd":0,"ind":8,"ty":4,"nm":"mask 3","parent":10,"td":1,"sr":1,"ks":{"o":{"a":0,"k":100,"ix":11},"r":{"a":0,"k":0,"ix":10},"p":{"a":0,"k":[0,0,0],"ix":2,"l":2},"a":{"a":0,"k":[0,0,0],"ix":1,"l":2},"s":{"a":0,"k":[100,100,100],"ix":6,"l":2}},"ao":0,"shapes":[{"ty":"gr","it":[{"ind":0,"ty":"sh","ix":1,"ks":{"a":0,"k":{"i":[[30,15],[30,-15],[-30,-15],[-30,15]],"o":[[-30,-15],[-30,15],[30,15],[30,-15]],"v":[[165,-135],[-165,-135],[-165,135],[165,135]],"c":true},"ix":2},"nm":"Path 1","mn":"ADBE Vector Shape - Group","hd":false},{"ty":"fl","c":{"a":0,"k":[1,0,0,1],"ix":4},"o":{"a":0,"k":100,"ix":5},"r":1,"bm":0,"nm":"Fill 1","mn":"ADBE Vector Graphic - Fill","hd":false},{"ty":"tr","p":{"a":0,"k":[0,0],"ix":2},"a":{"a":0,"k":[0,0],"ix":1},"s":{"a":0,"k":[100,100],"ix":3},"r":{"a":0,"k":0,"ix":6},"o":{"a":0,"k":100,"ix":7},"sk":{"a":0,"k":0,"ix":4},"sa":{"a":0,"k":0,"ix":5},"nm":"Transform"}],"nm":"rectangle","np":2,"cix":2,"bm":0,"ix":1,"mn":"ADBE Vector Group","hd":false}],"ip":-3,"op":1800,"st":0,"ct":1,"bm":0},{"ddd":0,"ind":9,"ty":4,"nm":"triangle 5","parent":7,"tt":1,"tp":8,"sr":1,"ks":{"o":{"a":0,"k":100,"ix":11},"r":{"a":0,"k":-540,"ix":10},"p":{"a":0,"k":[1.196,0,0],"ix":2,"l":2},"a":{"a":0,"k":[0,0,0],"ix":1,"l":2},"s":{"a":0,"k":[100,100,100],"ix":6,"l":2}},"ao":0,"shapes":[{"ty":"gr","it":[{"ind":0,"ty":"sh","ix":1,"ks":{"a":0,"k":{"i":[[0,0],[0,0],[0,0],[0,2.399],[0,0],[-1.993,-1.335]],"o":[[0,0],[0,0],[-1.993,1.335],[0,0],[0,-2.399],[0,0]],"v":[[15,-56.913],[15,56.913],[-10.331,73.874],[-15,71.381],[-15,-71.381],[-10.331,-73.874]],"c":true},"ix":2},"nm":"Path 1","mn":"ADBE Vector Shape - Group","hd":false},{"ty":"fl","c":{"a":0,"k":[0.922,0.902,0.937,1],"ix":4,"x":"var $bm_rt;\n$bm_rt = comp('wired-flat-2547-logo-youtube').layer('control').effect('primary')('Color');"},"o":{"a":0,"k":50,"ix":5},"r":1,"bm":0,"nm":".primary","mn":"ADBE Vector Graphic - Fill","hd":false,"cl":"primary"},{"ty":"tr","p":{"a":0,"k":[-41.375,0],"ix":2},"a":{"a":0,"k":[0,0],"ix":1},"s":{"a":0,"k":[100,100],"ix":3},"r":{"a":0,"k":0,"ix":6},"o":{"a":0,"k":100,"ix":7},"sk":{"a":0,"k":0,"ix":4},"sa":{"a":0,"k":0,"ix":5},"nm":"Transform"}],"nm":"triangle-shadow","np":2,"cix":2,"bm":1,"ix":1,"mn":"ADBE Vector Group","hd":false},{"ty":"gr","it":[{"ind":0,"ty":"sh","ix":1,"ks":{"a":0,"k":{"i":[[0,0],[1.775,1.188],[0,0],[0,-2.399],[0,0],[-1.993,1.335]],"o":[[1.775,-1.188],[0,0],[-1.993,-1.335],[0,0],[0,2.399],[0,0]],"v":[[54.973,2.493],[54.973,-2.493],[-51.635,-73.874],[-56.304,-71.381],[-56.304,71.381],[-51.635,73.874]],"c":true},"ix":2},"nm":"Path 1","mn":"ADBE Vector Shape - Group","hd":false},{"ty":"rd","nm":"Round Corners 1","r":{"a":0,"k":3,"ix":1},"ix":2,"mn":"ADBE Vector Filter - RC","hd":false},{"ty":"fl","c":{"a":0,"k":[0.922,0.902,0.937,1],"ix":4,"x":"var $bm_rt;\n$bm_rt = comp('wired-flat-2547-logo-youtube').layer('control').effect('primary')('Color');"},"o":{"a":0,"k":100,"ix":5},"r":1,"bm":0,"nm":".primary","mn":"ADBE Vector Graphic - Fill","hd":false,"cl":"primary"},{"ty":"tr","p":{"a":0,"k":[0,0],"ix":2},"a":{"a":0,"k":[0,0],"ix":1},"s":{"a":0,"k":[100,100],"ix":3},"r":{"a":0,"k":0,"ix":6},"o":{"a":0,"k":100,"ix":7},"sk":{"a":0,"k":0,"ix":4},"sa":{"a":0,"k":0,"ix":5},"nm":"Transform"}],"nm":"triangle","np":3,"cix":2,"bm":0,"ix":2,"mn":"ADBE Vector Group","hd":false}],"ip":0,"op":300,"st":0,"ct":1,"bm":0},{"ddd":0,"ind":10,"ty":3,"nm":"rectangle","sr":1,"ks":{"o":{"a":0,"k":100,"ix":11},"r":{"a":0,"k":0,"ix":10},"p":{"a":0,"k":[215,215,0],"ix":2,"l":2},"a":{"a":0,"k":[0,0,0],"ix":1,"l":2},"s":{"a":1,"k":[{"i":{"x":[0.18,0.18,0.18],"y":[1,1,1]},"o":{"x":[0.42,0.42,0.42],"y":[0,0,0]},"t":0,"s":[100,100,100]},{"t":30,"s":[61.3,61.3,100]}],"ix":6,"l":2}},"ao":0,"ip":0,"op":1800,"st":0,"ct":1,"bm":0},{"ddd":0,"ind":11,"ty":4,"nm":"rectangle 2","parent":10,"sr":1,"ks":{"o":{"a":0,"k":100,"ix":11},"r":{"a":0,"k":0,"ix":10},"p":{"a":0,"k":[0,0,0],"ix":2,"l":2},"a":{"a":0,"k":[0,0,0],"ix":1,"l":2},"s":{"a":0,"k":[100,100,100],"ix":6,"l":2}},"ao":0,"shapes":[{"ty":"gr","it":[{"ind":0,"ty":"sh","ix":1,"ks":{"a":0,"k":{"i":[[-30,15],[-81.856,-0.827],[13.496,-6.748],[-30,-15],[-66.938,-0.677],[16.504,8.252]],"o":[[16.504,-8.252],[-66.937,0.677],[-30,15],[13.496,6.748],[-81.857,0.827],[-30,-15]],"v":[[-82.501,-135],[104.999,-146.137],[-37.501,-135],[-37.501,135],[105.001,146.137],[-82.501,135]],"c":true},"ix":2},"nm":"Path 1","mn":"ADBE Vector Shape - Group","hd":false},{"ty":"fl","c":{"a":0,"k":[0.949,0.298,0,1],"ix":4,"x":"var $bm_rt;\n$bm_rt = comp('wired-flat-2547-logo-youtube').layer('control').effect('secondary')('Color');"},"o":{"a":0,"k":50,"ix":5},"r":1,"bm":0,"nm":".secondary","mn":"ADBE Vector Graphic - Fill","hd":false,"cl":"secondary"},{"ty":"tr","p":{"a":0,"k":[-82.5,0],"ix":2},"a":{"a":0,"k":[0,0],"ix":1},"s":{"a":0,"k":[100,100],"ix":3},"r":{"a":0,"k":0,"ix":6},"o":{"a":0,"k":100,"ix":7},"sk":{"a":0,"k":0,"ix":4},"sa":{"a":0,"k":0,"ix":5},"nm":"Transform"}],"nm":"rectangle-shadow","np":2,"cix":2,"bm":1,"ix":1,"mn":"ADBE Vector Group","hd":false},{"ty":"gr","it":[{"ind":0,"ty":"sh","ix":1,"ks":{"a":0,"k":{"i":[[30,15],[30,-15],[-30,-15],[-30,15]],"o":[[-30,-15],[-30,15],[30,15],[30,-15]],"v":[[165,-135],[-165,-135],[-165,135],[165,135]],"c":true},"ix":2},"nm":"Path 1","mn":"ADBE Vector Shape - Group","hd":false},{"ty":"fl","c":{"a":0,"k":[0.949,0.298,0,1],"ix":4,"x":"var $bm_rt;\n$bm_rt = comp('wired-flat-2547-logo-youtube').layer('control').effect('secondary')('Color');"},"o":{"a":0,"k":100,"ix":5},"r":1,"bm":0,"nm":".secondary","mn":"ADBE Vector Graphic - Fill","hd":false,"cl":"secondary"},{"ty":"tr","p":{"a":0,"k":[0,0],"ix":2},"a":{"a":0,"k":[0,0],"ix":1},"s":{"a":0,"k":[100,100],"ix":3},"r":{"a":0,"k":0,"ix":6},"o":{"a":0,"k":100,"ix":7},"sk":{"a":0,"k":0,"ix":4},"sa":{"a":0,"k":0,"ix":5},"nm":"Transform"}],"nm":"rectangle","np":2,"cix":2,"bm":0,"ix":2,"mn":"ADBE Vector Group","hd":false}],"ip":0,"op":300,"st":0,"ct":1,"bm":0}]},{"id":"comp_6","nm":"morph-square","fr":60,"layers":[{"ddd":0,"ind":2,"ty":4,"nm":"mask 2","td":1,"sr":1,"ks":{"o":{"a":0,"k":100,"ix":11},"r":{"a":0,"k":0,"ix":10},"p":{"a":0,"k":[215,215,0],"ix":2,"l":2},"a":{"a":0,"k":[0,0,0],"ix":1,"l":2},"s":{"a":0,"k":[100,100,100],"ix":6,"l":2}},"ao":0,"shapes":[{"ty":"gr","it":[{"ind":0,"ty":"sh","ix":1,"ks":{"a":1,"k":[{"i":{"x":0.833,"y":0.833},"o":{"x":0.167,"y":0.167},"t":7,"s":[{"i":[[0,0.199],[0,0],[11.046,0],[0,0],[0,-0.199],[0,0],[-11.046,0],[0,0]],"o":[[0,0],[0,-0.199],[0,0],[-11.046,0],[0,0],[0,0.199],[0,0],[11.046,0]],"v":[[160,-0.111],[160,-0.514],[146.875,-0.875],[-148.75,-0.875],[-160,-0.514],[-160,-0.111],[-148.75,0.25],[146.875,0.25]],"c":true}]},{"i":{"x":0.833,"y":0.833},"o":{"x":0.167,"y":0.167},"t":8,"s":[{"i":[[0,-5.423],[0,0],[11.046,0],[0,0],[0,5.423],[0,0],[-11.046,0],[0,0]],"o":[[0,0],[0,5.423],[0,0],[-11.046,0],[0,0],[0,-5.423],[0,0],[11.046,0]],"v":[[160,-1.305],[159.938,1.43],[143.375,11.25],[-144.438,11.25],[-160.062,1.43],[-160,-1.305],[-144.375,-11.125],[143.438,-11.125]],"c":true}]},{"i":{"x":0.034,"y":1},"o":{"x":0.068,"y":0.068},"t":9,"s":[{"i":[[0,-11.046],[0,0],[11.046,0],[0,0],[0,11.046],[0,0],[-11.046,0],[0,0]],"o":[[0,0],[0,11.046],[0,0],[-11.046,0],[0,0],[0,-11.046],[0,0],[11.046,0]],"v":[[160,-11.5],[160,10.875],[140,30.875],[-140,30.875],[-160,10.875],[-160,-11.5],[-140,-31.5],[140,-31.5]],"c":true}]},{"t":30,"s":[{"i":[[0,-11.046],[0,0],[11.046,0],[0,0],[0,11.046],[0,0],[-11.046,0],[0,0]],"o":[[0,0],[0,11.046],[0,0],[-11.046,0],[0,0],[0,-11.046],[0,0],[11.046,0]],"v":[[160,-140],[160,140],[140,160],[-140,160],[-160,140],[-160,-140],[-140,-160],[140,-160]],"c":true}]}],"ix":2},"nm":"Path 1","mn":"ADBE Vector Shape - Group","hd":false},{"ty":"fl","c":{"a":0,"k":[0.949019667682,0.298039215686,0,1],"ix":4},"o":{"a":0,"k":100,"ix":5},"r":1,"bm":0,"nm":".primary","mn":"ADBE Vector Graphic - Fill","hd":false,"cl":"primary"},{"ty":"tr","p":{"a":0,"k":[0,0],"ix":2},"a":{"a":0,"k":[0,0],"ix":1},"s":{"a":0,"k":[100,100],"ix":3},"r":{"a":0,"k":0,"ix":6},"o":{"a":0,"k":100,"ix":7},"sk":{"a":0,"k":0,"ix":4},"sa":{"a":0,"k":0,"ix":5},"nm":"Transform"}],"nm":"rect","np":2,"cix":2,"bm":0,"ix":1,"mn":"ADBE Vector Group","hd":false}],"ip":8,"op":300,"st":0,"ct":1,"bm":0},{"ddd":0,"ind":3,"ty":0,"nm":"awers","tt":2,"tp":2,"refId":"comp_5","sr":1,"ks":{"o":{"a":0,"k":100,"ix":11},"r":{"a":0,"k":0,"ix":10},"p":{"a":0,"k":[215,215,0],"ix":2,"l":2},"a":{"a":0,"k":[215,215,0],"ix":1,"l":2},"s":{"a":0,"k":[100,100,100],"ix":6,"l":2}},"ao":0,"w":430,"h":430,"ip":0,"op":1800,"st":0,"bm":0},{"ddd":0,"ind":4,"ty":4,"nm":"mask","td":1,"sr":1,"ks":{"o":{"a":0,"k":100,"ix":11},"r":{"a":0,"k":0,"ix":10},"p":{"a":0,"k":[215,215,0],"ix":2,"l":2},"a":{"a":0,"k":[0,0,0],"ix":1,"l":2},"s":{"a":0,"k":[100,100,100],"ix":6,"l":2}},"ao":0,"shapes":[{"ty":"gr","it":[{"ind":0,"ty":"sh","ix":1,"ks":{"a":1,"k":[{"i":{"x":0.833,"y":0.833},"o":{"x":0.167,"y":0.167},"t":7,"s":[{"i":[[0,0.199],[0,0],[11.046,0],[0,0],[0,-0.199],[0,0],[-11.046,0],[0,0]],"o":[[0,0],[0,-0.199],[0,0],[-11.046,0],[0,0],[0,0.199],[0,0],[11.046,0]],"v":[[160,-0.111],[160,-0.514],[146.875,-0.875],[-148.75,-0.875],[-160,-0.514],[-160,-0.111],[-148.75,0.25],[146.875,0.25]],"c":true}]},{"i":{"x":0.833,"y":0.833},"o":{"x":0.167,"y":0.167},"t":8,"s":[{"i":[[0,-5.423],[0,0],[11.046,0],[0,0],[0,5.423],[0,0],[-11.046,0],[0,0]],"o":[[0,0],[0,5.423],[0,0],[-11.046,0],[0,0],[0,-5.423],[0,0],[11.046,0]],"v":[[160,-1.305],[159.938,1.43],[143.375,11.25],[-144.438,11.25],[-160.062,1.43],[-160,-1.305],[-144.375,-11.125],[143.438,-11.125]],"c":true}]},{"i":{"x":0.034,"y":1},"o":{"x":0.068,"y":0.068},"t":9,"s":[{"i":[[0,-11.046],[0,0],[11.046,0],[0,0],[0,11.046],[0,0],[-11.046,0],[0,0]],"o":[[0,0],[0,11.046],[0,0],[-11.046,0],[0,0],[0,-11.046],[0,0],[11.046,0]],"v":[[160,-11.5],[160,10.875],[140,30.875],[-140,30.875],[-160,10.875],[-160,-11.5],[-140,-31.5],[140,-31.5]],"c":true}]},{"t":30,"s":[{"i":[[0,-11.046],[0,0],[11.046,0],[0,0],[0,11.046],[0,0],[-11.046,0],[0,0]],"o":[[0,0],[0,11.046],[0,0],[-11.046,0],[0,0],[0,-11.046],[0,0],[11.046,0]],"v":[[160,-140],[160,140],[140,160],[-140,160],[-160,140],[-160,-140],[-140,-160],[140,-160]],"c":true}]}],"ix":2},"nm":"Path 1","mn":"ADBE Vector Shape - Group","hd":false},{"ty":"fl","c":{"a":0,"k":[0.949019667682,0.298039215686,0,1],"ix":4},"o":{"a":0,"k":100,"ix":5},"r":1,"bm":0,"nm":".primary","mn":"ADBE Vector Graphic - Fill","hd":false,"cl":"primary"},{"ty":"tr","p":{"a":0,"k":[0,0],"ix":2},"a":{"a":0,"k":[0,0],"ix":1},"s":{"a":0,"k":[100,100],"ix":3},"r":{"a":0,"k":0,"ix":6},"o":{"a":0,"k":100,"ix":7},"sk":{"a":0,"k":0,"ix":4},"sa":{"a":0,"k":0,"ix":5},"nm":"Transform"}],"nm":"rect","np":2,"cix":2,"bm":0,"ix":1,"mn":"ADBE Vector Group","hd":false}],"ip":8,"op":300,"st":0,"ct":1,"bm":0},{"ddd":0,"ind":5,"ty":0,"nm":"rewers","tt":1,"tp":4,"refId":"comp_4","sr":1,"ks":{"o":{"a":0,"k":100,"ix":11},"r":{"a":0,"k":0,"ix":10},"p":{"a":0,"k":[215,215,0],"ix":2,"l":2},"a":{"a":0,"k":[215,215,0],"ix":1,"l":2},"s":{"a":0,"k":[100,100,100],"ix":6,"l":2}},"ao":0,"w":430,"h":430,"ip":0,"op":1800,"st":0,"bm":0},{"ddd":0,"ind":6,"ty":4,"nm":"rect 3","sr":1,"ks":{"o":{"a":0,"k":100,"ix":11},"r":{"a":0,"k":0,"ix":10},"p":{"a":0,"k":[215,215,0],"ix":2,"l":2},"a":{"a":0,"k":[0,0,0],"ix":1,"l":2},"s":{"a":0,"k":[100,100,100],"ix":6,"l":2}},"ao":0,"shapes":[{"ty":"gr","it":[{"ind":0,"ty":"sh","ix":1,"ks":{"a":1,"k":[{"i":{"x":0.833,"y":0.833},"o":{"x":0.167,"y":0.167},"t":7,"s":[{"i":[[0,0],[-11.046,0],[0,0],[0,0.199],[0,0],[-11.046,0],[0,0],[0,-0.199]],"o":[[0,0.199],[0,0],[-11.046,0],[0,0],[0,-0.199],[0,0],[-11.046,0],[0,0]],"v":[[-32.5,-0.111],[-21.25,0.25],[23.75,0.25],[12.5,-0.111],[12.5,-0.514],[23.75,-0.875],[-21.25,-0.875],[-32.5,-0.514]],"c":true}]},{"i":{"x":0.833,"y":0.833},"o":{"x":0.167,"y":0.167},"t":8,"s":[{"i":[[0,0],[-11.046,0],[0,0],[0,-5.423],[0,0],[-11.046,0],[0,0],[0,5.423]],"o":[[0,-5.423],[0,0],[-11.046,0],[0,0],[0,5.423],[0,0],[-11.046,0],[0,0]],"v":[[-32.5,-1.305],[-16.875,-11.125],[28.125,-11.125],[12.5,-1.305],[12.438,1.43],[28.062,11.25],[-16.938,11.25],[-32.562,1.43]],"c":true}]},{"i":{"x":0.034,"y":1},"o":{"x":0.068,"y":0.068},"t":9,"s":[{"i":[[0,0],[-11.046,0],[0,0],[0,-11.046],[0,0],[-11.046,0],[0,0],[0,11.046]],"o":[[0,-11.046],[0,0],[-11.046,0],[0,0],[0,11.046],[0,0],[-11.046,0],[0,0]],"v":[[-32.5,-11.5],[-12.5,-31.5],[32.5,-31.5],[12.5,-11.5],[12.5,10.875],[32.5,30.875],[-12.5,30.875],[-32.5,10.875]],"c":true}]},{"t":30,"s":[{"i":[[0,0],[-11.046,0],[0,0],[0,-11.046],[0,0],[-11.046,0],[0,0],[0,11.046]],"o":[[0,-11.046],[0,0],[-11.046,0],[0,0],[0,11.046],[0,0],[-11.046,0],[0,0]],"v":[[-32.5,-140],[-12.5,-160],[32.5,-160],[12.5,-140],[12.5,140],[32.5,160],[-12.5,160],[-32.5,140]],"c":true}]}],"ix":2},"nm":"Path 1","mn":"ADBE Vector Shape - Group","hd":false},{"ty":"fl","c":{"a":0,"k":[0.949,0.298,0,1],"ix":4,"x":"var $bm_rt;\n$bm_rt = comp('wired-flat-2547-logo-youtube').layer('control').effect('secondary')('Color');"},"o":{"a":0,"k":50,"ix":5},"r":1,"bm":0,"nm":".secondary","mn":"ADBE Vector Graphic - Fill","hd":false,"cl":"secondary"},{"ty":"tr","p":{"a":0,"k":[-127.5,0],"ix":2},"a":{"a":0,"k":[0,0],"ix":1},"s":{"a":0,"k":[100,100],"ix":3},"r":{"a":0,"k":0,"ix":6},"o":{"a":0,"k":100,"ix":7},"sk":{"a":0,"k":0,"ix":4},"sa":{"a":0,"k":0,"ix":5},"nm":"Transform"}],"nm":"rect-shadow","np":2,"cix":2,"bm":1,"ix":1,"mn":"ADBE Vector Group","hd":false},{"ty":"gr","it":[{"ind":0,"ty":"sh","ix":1,"ks":{"a":1,"k":[{"i":{"x":0.833,"y":0.833},"o":{"x":0.167,"y":0.167},"t":7,"s":[{"i":[[0,0.199],[0,0],[11.046,0],[0,0],[0,-0.199],[0,0],[-11.046,0],[0,0]],"o":[[0,0],[0,-0.199],[0,0],[-11.046,0],[0,0],[0,0.199],[0,0],[11.046,0]],"v":[[160,-0.111],[160,-0.514],[146.875,-0.875],[-148.75,-0.875],[-160,-0.514],[-160,-0.111],[-148.75,0.25],[146.875,0.25]],"c":true}]},{"i":{"x":0.833,"y":0.833},"o":{"x":0.167,"y":0.167},"t":8,"s":[{"i":[[0,-5.423],[0,0],[11.046,0],[0,0],[0,5.423],[0,0],[-11.046,0],[0,0]],"o":[[0,0],[0,5.423],[0,0],[-11.046,0],[0,0],[0,-5.423],[0,0],[11.046,0]],"v":[[160,-1.305],[159.938,1.43],[143.375,11.25],[-144.438,11.25],[-160.062,1.43],[-160,-1.305],[-144.375,-11.125],[143.438,-11.125]],"c":true}]},{"i":{"x":0.034,"y":1},"o":{"x":0.068,"y":0.068},"t":9,"s":[{"i":[[0,-11.046],[0,0],[11.046,0],[0,0],[0,11.046],[0,0],[-11.046,0],[0,0]],"o":[[0,0],[0,11.046],[0,0],[-11.046,0],[0,0],[0,-11.046],[0,0],[11.046,0]],"v":[[160,-11.5],[160,10.875],[140,30.875],[-140,30.875],[-160,10.875],[-160,-11.5],[-140,-31.5],[140,-31.5]],"c":true}]},{"t":30,"s":[{"i":[[0,-11.046],[0,0],[11.046,0],[0,0],[0,11.046],[0,0],[-11.046,0],[0,0]],"o":[[0,0],[0,11.046],[0,0],[-11.046,0],[0,0],[0,-11.046],[0,0],[11.046,0]],"v":[[160,-140],[160,140],[140,160],[-140,160],[-160,140],[-160,-140],[-140,-160],[140,-160]],"c":true}]}],"ix":2},"nm":"Path 1","mn":"ADBE Vector Shape - Group","hd":false},{"ty":"fl","c":{"a":0,"k":[0.949,0.298,0,1],"ix":4,"x":"var $bm_rt;\n$bm_rt = comp('wired-flat-2547-logo-youtube').layer('control').effect('secondary')('Color');"},"o":{"a":0,"k":100,"ix":5},"r":1,"bm":0,"nm":".secondary","mn":"ADBE Vector Graphic - Fill","hd":false,"cl":"secondary"},{"ty":"tr","p":{"a":0,"k":[0,0],"ix":2},"a":{"a":0,"k":[0,0],"ix":1},"s":{"a":0,"k":[100,100],"ix":3},"r":{"a":0,"k":0,"ix":6},"o":{"a":0,"k":100,"ix":7},"sk":{"a":0,"k":0,"ix":4},"sa":{"a":0,"k":0,"ix":5},"nm":"Transform"}],"nm":"rect","np":2,"cix":2,"bm":0,"ix":2,"mn":"ADBE Vector Group","hd":false}],"ip":8,"op":300,"st":0,"ct":1,"bm":0}]}],"layers":[{"ddd":0,"ind":1,"ty":3,"nm":"control","sr":1,"ks":{"o":{"a":0,"k":0,"ix":11},"r":{"a":0,"k":0,"ix":10},"p":{"a":0,"k":[0,0],"ix":2,"l":2},"a":{"a":0,"k":[0,0,0],"ix":1,"l":2},"s":{"a":0,"k":[100,100,100],"ix":6,"l":2}},"ao":0,"ef":[{"ty":5,"nm":"primary","np":3,"mn":"ADBE Color Control","ix":1,"en":1,"ef":[{"ty":2,"nm":"Color","mn":"ADBE Color Control-0001","ix":1,"v":{"a":0,"k":[0.922,0.902,0.937],"ix":1}}]},{"ty":5,"nm":"secondary","np":3,"mn":"ADBE Color Control","ix":2,"en":1,"ef":[{"ty":2,"nm":"Color","mn":"ADBE Color Control-0001","ix":1,"v":{"a":0,"k":[0.949,0.298,0],"ix":1}}]},{"ty":5,"nm":"tertiary","np":3,"mn":"ADBE Color Control","ix":3,"en":1,"ef":[{"ty":2,"nm":"Color","mn":"ADBE Color Control-0001","ix":1,"v":{"a":0,"k":[0.227,0.2,0.278],"ix":1}}]}],"ip":0,"op":251,"st":0,"bm":0},{"ddd":0,"ind":2,"ty":0,"nm":"in-reveal","refId":"comp_0","sr":1,"ks":{"o":{"a":0,"k":100,"ix":11},"r":{"a":0,"k":0,"ix":10},"p":{"a":0,"k":[215,215,0],"ix":2,"l":2},"a":{"a":0,"k":[215,215,0],"ix":1,"l":2},"s":{"a":0,"k":[100,100,100],"ix":6,"l":2}},"ao":0,"w":430,"h":430,"ip":0,"op":70,"st":0,"bm":0},{"ddd":0,"ind":3,"ty":0,"nm":"hover-pinch","refId":"comp_1","sr":1,"ks":{"o":{"a":0,"k":100,"ix":11},"r":{"a":0,"k":0,"ix":10},"p":{"a":0,"k":[215,215,0],"ix":2,"l":2},"a":{"a":0,"k":[215,215,0],"ix":1,"l":2},"s":{"a":0,"k":[100,100,100],"ix":6,"l":2}},"ao":0,"w":430,"h":430,"ip":70,"op":140,"st":70,"bm":0},{"ddd":0,"ind":4,"ty":0,"nm":"morph-logotype","refId":"comp_2","sr":1,"ks":{"o":{"a":0,"k":100,"ix":11},"r":{"a":0,"k":0,"ix":10},"p":{"a":0,"k":[215,215,0],"ix":2,"l":2},"a":{"a":0,"k":[215,215,0],"ix":1,"l":2},"s":{"a":0,"k":[100,100,100],"ix":6,"l":2}},"ao":0,"w":430,"h":430,"ip":140,"op":180,"st":140,"bm":0},{"ddd":0,"ind":5,"ty":0,"nm":"morph-circle","refId":"comp_3","sr":1,"ks":{"o":{"a":0,"k":100,"ix":11},"r":{"a":0,"k":0,"ix":10},"p":{"a":0,"k":[215,215,0],"ix":2,"l":2},"a":{"a":0,"k":[215,215,0],"ix":1,"l":2},"s":{"a":0,"k":[100,100,100],"ix":6,"l":2}},"ao":0,"w":430,"h":430,"ip":180,"op":220,"st":180,"bm":0},{"ddd":0,"ind":6,"ty":0,"nm":"morph-square","refId":"comp_6","sr":1,"ks":{"o":{"a":0,"k":100,"ix":11},"r":{"a":0,"k":0,"ix":10},"p":{"a":0,"k":[215,215,0],"ix":2,"l":2},"a":{"a":0,"k":[215,215,0],"ix":1,"l":2},"s":{"a":0,"k":[100,100,100],"ix":6,"l":2}},"ao":0,"w":430,"h":430,"ip":220,"op":260,"st":220,"bm":0}],"markers":[{"tm":0,"cm":"in-reveal","dr":60},{"tm":70,"cm":"default:hover-pinch","dr":60},{"tm":140,"cm":"morph-logotype","dr":30},{"tm":180,"cm":"morph-circle","dr":30},{"tm":220,"cm":"morph-square","dr":30}],"props":{}}